{"row0": {" TW": "1"," LW": "1"," Movie": "The Chronicles of Narnia: The Voyage of the Dawn Treader"," Studio": "n/a"," Weekend Gross": "$11,034"," Change": "-23.7%"," Screens / Avg.": "3"," Gross-to-Date": "$3,678"," Week": "$50,353","": "3"},
"row1": {" TW": "2"," LW": "2"," Movie": "Unstoppable"," Studio": "n/a"," Weekend Gross": "$3,286"," Change": "+10.7%"," Screens / Avg.": "1"," Gross-to-Date": "$3,286"," Week": "$75,719","": "7"},
"row2": {" TW": "3"," LW": "3"," Movie": "Faster"," Studio": "Sony"," Weekend Gross": "$2,958"," Change": "+1.8%"," Screens / Avg.": "1"," Gross-to-Date": "$2,958"," Week": "$21,592","": "4"},
"row3": {" TW": "4"," LW": "4"," Movie": "The Social Network"," Studio": "Sony"," Weekend Gross": "$350"," Change": "-46.4%"," Screens / Avg.": "1"," Gross-to-Date": "$350"," Week": "$34,257","": "9"},
"row4": {" TW": "5"," LW": "6"," Movie": "Eat Pray Love"," Studio": "Sony"," Weekend Gross": "$321"," Change": "+25.9%"," Screens / Avg.": "1"," Gross-to-Date": "$321"," Week": "$88,178","": "12"},
"row5": {" TW": "6"," LW": "7"," Movie": "Easy A"," Studio": "Sony"," Weekend Gross": "$223"," Change": "+21.9%"," Screens / Avg.": "1"," Gross-to-Date": "$223"," Week": "$4,889","": "5"},
"row6": {" TW": "7"," LW": "5"," Movie": "Machete"," Studio": "Sony"," Weekend Gross": "$127"," Change": "-52.1%"," Screens / Avg.": "1"," Gross-to-Date": "$127"," Week": "$9,236","": "6"},
"row7": {" TW": " TW"," LW": " LW"," Movie": " Movie"," Studio": " Studio"," Weekend Gross": " Weekend Gross"," Change": " Change"," Screens / Avg.": " Screens / Avg."," Gross-to-Date": " Gross-to-Date"," Week": " Week","": ""},
"row8": {" TW": "1"," LW": "1"," Movie": "The Chronicles of Narnia: The Voyage of the Dawn Treader"," Studio": "n/a"," Weekend Gross": "$14,464"," Change": "+27.9%"," Screens / Avg.": "3"," Gross-to-Date": "$4,821"," Week": "$35,382","": "2"},
"row9": {" TW": "2"," LW": "3"," Movie": "Unstoppable"," Studio": "n/a"," Weekend Gross": "$2,968"," Change": "+15.2%"," Screens / Avg.": "1"," Gross-to-Date": "$2,968"," Week": "$70,777","": "6"},
"row10": {" TW": "3"," LW": "2"," Movie": "Faster"," Studio": "Sony"," Weekend Gross": "$2,905"," Change": "-8.5%"," Screens / Avg.": "1"," Gross-to-Date": "$2,905"," Week": "$17,159","": "3"},
"row11": {" TW": "4"," LW": "5"," Movie": "The Social Network"," Studio": "Sony"," Weekend Gross": "$653"," Change": "+86.6%"," Screens / Avg.": "1"," Gross-to-Date": "$653"," Week": "$33,676","": "8"},
"row12": {" TW": "5"," LW": "7"," Movie": "Machete"," Studio": "Sony"," Weekend Gross": "$265"," Change": "+38.7%"," Screens / Avg.": "1"," Gross-to-Date": "$265"," Week": "$9,085","": "5"},
"row13": {" TW": "6"," LW": "4"," Movie": "Eat Pray Love"," Studio": "Sony"," Weekend Gross": "$255"," Change": "-44.4%"," Screens / Avg.": "1"," Gross-to-Date": "$255"," Week": "$87,711","": "11"},
"row14": {" TW": "7"," LW": "6"," Movie": "Easy A"," Studio": "Sony"," Weekend Gross": "$183"," Change": "-46.5%"," Screens / Avg.": "1"," Gross-to-Date": "$183"," Week": "$4,578","": "4"},
"row15": {" TW": "8"," LW": "8"," Movie": "Vampires Suck"," Studio": "n/a"," Weekend Gross": "$127"," Change": "+76.4%"," Screens / Avg.": "1"," Gross-to-Date": "$127"," Week": "$7,679","": "6"},
"row16": {" TW": " TW"," LW": " LW"," Movie": " Movie"," Studio": " Studio"," Weekend Gross": " Weekend Gross"," Change": " Change"," Screens / Avg.": " Screens / Avg."," Gross-to-Date": " Gross-to-Date"," Week": " Week","": ""},
"row17": {" TW": "1"," LW": "N"," Movie": "The Chronicles of Narnia: The Voyage of the Dawn Treader"," Studio": "n/a"," Weekend Gross": "$11,308"," Change": "-"," Screens / Avg.": "3"," Gross-to-Date": "$3,769"," Week": "$16,175","": "1"},
"row18": {" TW": "2"," LW": "1"," Movie": "Faster"," Studio": "Sony"," Weekend Gross": "$3,175"," Change": "-53.4%"," Screens / Avg.": "1"," Gross-to-Date": "$3,175"," Week": "$13,106","": "2"},
"row19": {" TW": "3"," LW": "2"," Movie": "Unstoppable"," Studio": "n/a"," Weekend Gross": "$2,576"," Change": "-47.9%"," Screens / Avg.": "1"," Gross-to-Date": "$2,576"," Week": "$66,273","": "5"},
"row20": {" TW": "4"," LW": "5"," Movie": "Eat Pray Love"," Studio": "Sony"," Weekend Gross": "$459"," Change": "-48.0%"," Screens / Avg.": "1"," Gross-to-Date": "$459"," Week": "$87,393","": "10"},
"row21": {" TW": "5"," LW": "3"," Movie": "The Social Network"," Studio": "Sony"," Weekend Gross": "$350"," Change": "-80.0%"," Screens / Avg.": "1"," Gross-to-Date": "$350"," Week": "$32,753","": "7"},
"row22": {" TW": "6"," LW": "4"," Movie": "Easy A"," Studio": "Sony"," Weekend Gross": "$342"," Change": "-66.2%"," Screens / Avg.": "1"," Gross-to-Date": "$342"," Week": "$4,164","": "3"},
"row23": {" TW": "7"," LW": "6"," Movie": "Machete"," Studio": "Sony"," Weekend Gross": "$191"," Change": "-72.5%"," Screens / Avg.": "1"," Gross-to-Date": "$191"," Week": "$8,772","": "4"},
"row24": {" TW": "8"," LW": "7"," Movie": "Vampires Suck"," Studio": "n/a"," Weekend Gross": "$72"," Change": "-86.3%"," Screens / Avg.": "1"," Gross-to-Date": "$72"," Week": "$7,408","": "5"},
"row25": {" TW": " TW"," LW": " LW"," Movie": " Movie"," Studio": " Studio"," Weekend Gross": " Weekend Gross"," Change": " Change"," Screens / Avg.": " Screens / Avg."," Gross-to-Date": " Gross-to-Date"," Week": " Week","": ""},
"row26": {" TW": "1"," LW": "N"," Movie": "Faster"," Studio": "Sony"," Weekend Gross": "$6,817"," Change": "-"," Screens / Avg.": "1"," Gross-to-Date": "$6,817"," Week": "$6,817","": "1"},
"row27": {" TW": "2"," LW": "1"," Movie": "Unstoppable"," Studio": "n/a"," Weekend Gross": "$4,944"," Change": "-27.2%"," Screens / Avg.": "1"," Gross-to-Date": "$4,944"," Week": "$62,780","": "4"},
"row28": {" TW": "3"," LW": "2"," Movie": "The Social Network"," Studio": "Sony"," Weekend Gross": "$1,753"," Change": "+10.9%"," Screens / Avg.": "1"," Gross-to-Date": "$1,753"," Week": "$31,804","": "6"},
"row29": {" TW": "4"," LW": "3"," Movie": "Easy A"," Studio": "Sony"," Weekend Gross": "$1,011"," Change": "-34.6%"," Screens / Avg.": "1"," Gross-to-Date": "$1,011"," Week": "$3,329","": "2"},
"row30": {" TW": "5"," LW": "4"," Movie": "Eat Pray Love"," Studio": "Sony"," Weekend Gross": "$883"," Change": "-42.2%"," Screens / Avg.": "1"," Gross-to-Date": "$883"," Week": "$86,417","": "9"},
"row31": {" TW": "6"," LW": "5"," Movie": "Machete"," Studio": "Sony"," Weekend Gross": "$695"," Change": "-52.9%"," Screens / Avg.": "1"," Gross-to-Date": "$695"," Week": "$8,064","": "3"},
"row32": {" TW": "7"," LW": "7"," Movie": "Vampires Suck"," Studio": "n/a"," Weekend Gross": "$525"," Change": "-26.7%"," Screens / Avg.": "1"," Gross-to-Date": "$525"," Week": "$7,233","": "4"},
"row33": {" TW": "8"," LW": "8"," Movie": "Marmaduke"," Studio": "n/a"," Weekend Gross": "$446"," Change": "-19.9%"," Screens / Avg.": "1"," Gross-to-Date": "$446"," Week": "$26,846","": "13"},
"row34": {" TW": " TW"," LW": " LW"," Movie": " Movie"," Studio": " Studio"," Weekend Gross": " Weekend Gross"," Change": " Change"," Screens / Avg.": " Screens / Avg."," Gross-to-Date": " Gross-to-Date"," Week": " Week","": ""},
"row35": {" TW": "1"," LW": "1"," Movie": "Unstoppable"," Studio": "n/a"," Weekend Gross": "$6,793"," Change": "-58.0%"," Screens / Avg.": "1"," Gross-to-Date": "$6,793"," Week": "$56,252","": "3"},
"row36": {" TW": "2"," LW": "4"," Movie": "The Social Network"," Studio": "Sony"," Weekend Gross": "$1,581"," Change": "-55.7%"," Screens / Avg.": "1"," Gross-to-Date": "$1,581"," Week": "$29,233","": "5"},
"row37": {" TW": "3"," LW": "N"," Movie": "Easy A"," Studio": "Sony"," Weekend Gross": "$1,546"," Change": "-"," Screens / Avg.": "1"," Gross-to-Date": "$1,546"," Week": "$1,546","": "1"},
"row38": {" TW": "4"," LW": "3"," Movie": "Eat Pray Love"," Studio": "Sony"," Weekend Gross": "$1,528"," Change": "-60.7%"," Screens / Avg.": "1"," Gross-to-Date": "$1,528"," Week": "$85,008","": "8"},
"row39": {" TW": "5"," LW": "2"," Movie": "Machete"," Studio": "Sony"," Weekend Gross": "$1,475"," Change": "-68.6%"," Screens / Avg.": "1"," Gross-to-Date": "$1,475"," Week": "$6,851","": "2"},
"row40": {" TW": "6"," LW": "5"," Movie": "Takers"," Studio": "Sony"," Weekend Gross": "$931"," Change": "-65.0%"," Screens / Avg.": "1"," Gross-to-Date": "$931"," Week": "$33,975","": "8"},
"row41": {" TW": "7"," LW": "6"," Movie": "Vampires Suck"," Studio": "n/a"," Weekend Gross": "$716"," Change": "-72.8%"," Screens / Avg.": "1"," Gross-to-Date": "$716"," Week": "$6,318","": "3"},
"row42": {" TW": "8"," LW": "7"," Movie": "Marmaduke"," Studio": "n/a"," Weekend Gross": "$557"," Change": "-71.7%"," Screens / Avg.": "1"," Gross-to-Date": "$557"," Week": "$26,202","": "12"},
"row43": {" TW": "9"," LW": "8"," Movie": "Wall Street: Money Never Sleeps"," Studio": "n/a"," Weekend Gross": "$469"," Change": "-14.6%"," Screens / Avg.": "1"," Gross-to-Date": "$469"," Week": "$39,761","": "10"},
"row44": {" TW": " TW"," LW": " LW"," Movie": " Movie"," Studio": " Studio"," Weekend Gross": " Weekend Gross"," Change": " Change"," Screens / Avg.": " Screens / Avg."," Gross-to-Date": " Gross-to-Date"," Week": " Week","": ""},
"row45": {" TW": "1"," LW": "1"," Movie": "Unstoppable"," Studio": "n/a"," Weekend Gross": "$16,164"," Change": "+43.5%"," Screens / Avg.": "1"," Gross-to-Date": "$16,164"," Week": "$46,873","": "2"},
"row46": {" TW": "2"," LW": "N"," Movie": "Machete"," Studio": "Sony"," Weekend Gross": "$4,690"," Change": "-"," Screens / Avg.": "1"," Gross-to-Date": "$4,690"," Week": "$4,690","": "1"},
"row47": {" TW": "3"," LW": "3"," Movie": "Eat Pray Love"," Studio": "Sony"," Weekend Gross": "$3,891"," Change": "+15.6%"," Screens / Avg.": "1"," Gross-to-Date": "$3,891"," Week": "$82,358","": "7"},
"row48": {" TW": "4"," LW": "2"," Movie": "The Social Network"," Studio": "Sony"," Weekend Gross": "$3,568"," Change": "-14.3%"," Screens / Avg.": "1"," Gross-to-Date": "$3,568"," Week": "$26,387","": "4"},
"row49": {" TW": "5"," LW": "4"," Movie": "Takers"," Studio": "Sony"," Weekend Gross": "$2,658"," Change": "+145.7%"," Screens / Avg.": "1"," Gross-to-Date": "$2,658"," Week": "$32,296","": "7"},
"row50": {" TW": "6"," LW": "-"," Movie": "Vampires Suck"," Studio": "n/a"," Weekend Gross": "$2,634"," Change": "-"," Screens / Avg.": "1"," Gross-to-Date": "$2,634"," Week": "$5,475","": "2"},
"row51": {" TW": "7"," LW": "5"," Movie": "Marmaduke"," Studio": "n/a"," Weekend Gross": "$1,966"," Change": "+92.9%"," Screens / Avg.": "1"," Gross-to-Date": "$1,966"," Week": "$25,581","": "11"},
"row52": {" TW": "8"," LW": "6"," Movie": "Wall Street: Money Never Sleeps"," Studio": "n/a"," Weekend Gross": "$549"," Change": "-37.3%"," Screens / Avg.": "1"," Gross-to-Date": "$549"," Week": "$39,212","": "9"},
"row53": {" TW": " TW"," LW": " LW"," Movie": " Movie"," Studio": " Studio"," Weekend Gross": " Weekend Gross"," Change": " Change"," Screens / Avg.": " Screens / Avg."," Gross-to-Date": " Gross-to-Date"," Week": " Week","": ""},
"row54": {" TW": "1"," LW": "N"," Movie": "Unstoppable"," Studio": "n/a"," Weekend Gross": "$11,265"," Change": "-"," Screens / Avg.": "1"," Gross-to-Date": "$11,265"," Week": "$25,159","": "1"},
"row55": {" TW": "2"," LW": "1"," Movie": "The Social Network"," Studio": "Sony"," Weekend Gross": "$4,162"," Change": "-28.5%"," Screens / Avg.": "1"," Gross-to-Date": "$4,162"," Week": "$19,536","": "3"},
"row56": {" TW": "3"," LW": "2"," Movie": "Eat Pray Love"," Studio": "Sony"," Weekend Gross": "$3,366"," Change": "-23.0%"," Screens / Avg.": "1"," Gross-to-Date": "$3,366"," Week": "$75,030","": "6"},
"row57": {" TW": "4"," LW": "3"," Movie": "Takers"," Studio": "Sony"," Weekend Gross": "$1,082"," Change": "-36.8%"," Screens / Avg.": "1"," Gross-to-Date": "$1,082"," Week": "$27,187","": "6"},
"row58": {" TW": "5"," LW": "8"," Movie": "Marmaduke"," Studio": "n/a"," Weekend Gross": "$1,019"," Change": "+100.2%"," Screens / Avg.": "1"," Gross-to-Date": "$1,019"," Week": "$22,995","": "10"},
"row59": {" TW": "6"," LW": "6"," Movie": "Wall Street: Money Never Sleeps"," Studio": "n/a"," Weekend Gross": "$875"," Change": "-12.1%"," Screens / Avg.": "1"," Gross-to-Date": "$875"," Week": "$38,592","": "8"},
"row60": {" TW": "7"," LW": "5"," Movie": "The Other Guys"," Studio": "Sony"," Weekend Gross": "$828"," Change": "-26.7%"," Screens / Avg.": "1"," Gross-to-Date": "$828"," Week": "$40,489","": "9"},
"row61": {" TW": "8"," LW": "4"," Movie": "Salt"," Studio": "Sony"," Weekend Gross": "$589"," Change": "-50.7%"," Screens / Avg.": "1"," Gross-to-Date": "$589"," Week": "$194,499","": "17"},
"row62": {" TW": " TW"," LW": " LW"," Movie": " Movie"," Studio": " Studio"," Weekend Gross": " Weekend Gross"," Change": " Change"," Screens / Avg.": " Screens / Avg."," Gross-to-Date": " Gross-to-Date"," Week": " Week","": ""},
"row63": {" TW": "1"," LW": "2"," Movie": "The Social Network"," Studio": "Sony"," Weekend Gross": "$5,817"," Change": "+4.0%"," Screens / Avg.": "1"," Gross-to-Date": "$5,817"," Week": "$13,910","": "2"},
"row64": {" TW": "2"," LW": "1"," Movie": "Eat Pray Love"," Studio": "Sony"," Weekend Gross": "$4,371"," Change": "-30.7%"," Screens / Avg.": "1"," Gross-to-Date": "$4,371"," Week": "$70,093","": "5"},
"row65": {" TW": "3"," LW": "3"," Movie": "Takers"," Studio": "Sony"," Weekend Gross": "$1,711"," Change": "-40.9%"," Screens / Avg.": "1"," Gross-to-Date": "$1,711"," Week": "$25,731","": "5"},
"row66": {" TW": "4"," LW": "5"," Movie": "Salt"," Studio": "Sony"," Weekend Gross": "$1,194"," Change": "-21.2%"," Screens / Avg.": "1"," Gross-to-Date": "$1,194"," Week": "$193,568","": "16"},
"row67": {" TW": "5"," LW": "6"," Movie": "The Other Guys"," Studio": "Sony"," Weekend Gross": "$1,130"," Change": "-12.3%"," Screens / Avg.": "1"," Gross-to-Date": "$1,130"," Week": "$39,383","": "8"},
"row68": {" TW": "6"," LW": "4"," Movie": "Wall Street: Money Never Sleeps"," Studio": "n/a"," Weekend Gross": "$995"," Change": "-43.9%"," Screens / Avg.": "1"," Gross-to-Date": "$995"," Week": "$36,849","": "7"},
"row69": {" TW": "7"," LW": "8"," Movie": "Grown Ups"," Studio": "Sony"," Weekend Gross": "$517"," Change": "+27.3%"," Screens / Avg.": "1"," Gross-to-Date": "$517"," Week": "$77,695","": "14"},
"row70": {" TW": "8"," LW": "7"," Movie": "Marmaduke"," Studio": "n/a"," Weekend Gross": "$509"," Change": "-7.3%"," Screens / Avg.": "1"," Gross-to-Date": "$509"," Week": "$20,408","": "9"},
"row71": {" TW": " TW"," LW": " LW"," Movie": " Movie"," Studio": " Studio"," Weekend Gross": " Weekend Gross"," Change": " Change"," Screens / Avg.": " Screens / Avg."," Gross-to-Date": " Gross-to-Date"," Week": " Week","": ""},
"row72": {" TW": "1"," LW": "1"," Movie": "Eat Pray Love"," Studio": "Sony"," Weekend Gross": "$6,311"," Change": "-31.8%"," Screens / Avg.": "1"," Gross-to-Date": "$6,311"," Week": "$63,417","": "4"},
"row73": {" TW": "2"," LW": "N"," Movie": "The Social Network"," Studio": "Sony"," Weekend Gross": "$5,594"," Change": "-"," Screens / Avg.": "1"," Gross-to-Date": "$5,594"," Week": "$5,594","": "1"},
"row74": {" TW": "3"," LW": "2"," Movie": "Takers"," Studio": "Sony"," Weekend Gross": "$2,897"," Change": "-8.3%"," Screens / Avg.": "1"," Gross-to-Date": "$2,897"," Week": "$23,216","": "4"},
"row75": {" TW": "4"," LW": "3"," Movie": "Wall Street: Money Never Sleeps"," Studio": "n/a"," Weekend Gross": "$1,775"," Change": "-3.0%"," Screens / Avg.": "1"," Gross-to-Date": "$1,775"," Week": "$35,530","": "6"},
"row76": {" TW": "5"," LW": "4"," Movie": "Salt"," Studio": "Sony"," Weekend Gross": "$1,515"," Change": "+20.5%"," Screens / Avg.": "1"," Gross-to-Date": "$1,515"," Week": "$191,831","": "15"},
"row77": {" TW": "6"," LW": "6"," Movie": "The Other Guys"," Studio": "Sony"," Weekend Gross": "$1,289"," Change": "+54.2%"," Screens / Avg.": "1"," Gross-to-Date": "$1,289"," Week": "$37,911","": "7"},
"row78": {" TW": "7"," LW": "5"," Movie": "Marmaduke"," Studio": "n/a"," Weekend Gross": "$549"," Change": "-54.9%"," Screens / Avg.": "1"," Gross-to-Date": "$549"," Week": "$19,662","": "8"},
"row79": {" TW": "8"," LW": "7"," Movie": "Grown Ups"," Studio": "Sony"," Weekend Gross": "$406"," Change": "+6.3%"," Screens / Avg.": "1"," Gross-to-Date": "$406"," Week": "$77,075","": "13"},
"row80": {" TW": " TW"," LW": " LW"," Movie": " Movie"," Studio": " Studio"," Weekend Gross": " Weekend Gross"," Change": " Change"," Screens / Avg.": " Screens / Avg."," Gross-to-Date": " Gross-to-Date"," Week": " Week","": ""},
"row81": {" TW": "1"," LW": "1"," Movie": "Eat Pray Love"," Studio": "Sony"," Weekend Gross": "$9,252"," Change": "-35.4%"," Screens / Avg.": "1"," Gross-to-Date": "$9,252"," Week": "$54,295","": "3"},
"row82": {" TW": "2"," LW": "2"," Movie": "Takers"," Studio": "Sony"," Weekend Gross": "$3,159"," Change": "-28.2%"," Screens / Avg.": "1"," Gross-to-Date": "$3,159"," Week": "$19,277","": "3"},
"row83": {" TW": "3"," LW": "3"," Movie": "Wall Street: Money Never Sleeps"," Studio": "n/a"," Weekend Gross": "$1,830"," Change": "-37.0%"," Screens / Avg.": "1"," Gross-to-Date": "$1,830"," Week": "$33,389","": "5"},
"row84": {" TW": "4"," LW": "6"," Movie": "Salt"," Studio": "Sony"," Weekend Gross": "$1,257"," Change": "-29.5%"," Screens / Avg.": "1"," Gross-to-Date": "$1,257"," Week": "$189,926","": "14"},
"row85": {" TW": "5"," LW": "7"," Movie": "Marmaduke"," Studio": "n/a"," Weekend Gross": "$1,218"," Change": "+0.3%"," Screens / Avg.": "1"," Gross-to-Date": "$1,218"," Week": "$19,065","": "7"},
"row86": {" TW": "6"," LW": "4"," Movie": "The Other Guys"," Studio": "Sony"," Weekend Gross": "$836"," Change": "-68.2%"," Screens / Avg.": "1"," Gross-to-Date": "$836"," Week": "$36,303","": "6"},
"row87": {" TW": "7"," LW": "5"," Movie": "Grown Ups"," Studio": "Sony"," Weekend Gross": "$382"," Change": "-79.3%"," Screens / Avg.": "1"," Gross-to-Date": "$382"," Week": "$76,470","": "12"},
"row88": {" TW": " TW"," LW": " LW"," Movie": " Movie"," Studio": " Studio"," Weekend Gross": " Weekend Gross"," Change": " Change"," Screens / Avg.": " Screens / Avg."," Gross-to-Date": " Gross-to-Date"," Week": " Week","": ""},
"row89": {" TW": "1"," LW": "1"," Movie": "Eat Pray Love"," Studio": "Sony"," Weekend Gross": "$14,324"," Change": "-25.2%"," Screens / Avg.": "1"," Gross-to-Date": "$14,324"," Week": "$40,450","": "2"},
"row90": {" TW": "2"," LW": "2"," Movie": "Takers"," Studio": "Sony"," Weekend Gross": "$4,398"," Change": "-51.2%"," Screens / Avg.": "1"," Gross-to-Date": "$4,398"," Week": "$15,043","": "2"},
"row91": {" TW": "3"," LW": "4"," Movie": "Wall Street: Money Never Sleeps"," Studio": "n/a"," Weekend Gross": "$2,905"," Change": "-25.3%"," Screens / Avg.": "1"," Gross-to-Date": "$2,905"," Week": "$30,453","": "4"},
"row92": {" TW": "4"," LW": "3"," Movie": "The Other Guys"," Studio": "Sony"," Weekend Gross": "$2,629"," Change": "-32.6%"," Screens / Avg.": "1"," Gross-to-Date": "$2,629"," Week": "$34,871","": "5"},
"row93": {" TW": "5"," LW": "5"," Movie": "Grown Ups"," Studio": "Sony"," Weekend Gross": "$1,846"," Change": "-13.1%"," Screens / Avg.": "1"," Gross-to-Date": "$1,846"," Week": "$75,642","": "11"},
"row94": {" TW": "6"," LW": "6"," Movie": "Salt"," Studio": "Sony"," Weekend Gross": "$1,783"," Change": "-11.1%"," Screens / Avg.": "1"," Gross-to-Date": "$1,783"," Week": "$188,263","": "13"},
"row95": {" TW": "7"," LW": "7"," Movie": "Marmaduke"," Studio": "n/a"," Weekend Gross": "$1,215"," Change": "+10.9%"," Screens / Avg.": "1"," Gross-to-Date": "$1,215"," Week": "$17,688","": "6"},
"row96": {" TW": "8"," LW": "8"," Movie": "Knight & Day"," Studio": "n/a"," Weekend Gross": "$422"," Change": "-5.4%"," Screens / Avg.": "1"," Gross-to-Date": "$422"," Week": "$103,401","": "16"},
"row97": {" TW": "9"," LW": "9"," Movie": "Cyrus"," Studio": "n/a"," Weekend Gross": "$72"," Change": "-54.7%"," Screens / Avg.": "1"," Gross-to-Date": "$72"," Week": "$4,348","": "6"},
"row98": {" TW": " TW"," LW": " LW"," Movie": " Movie"," Studio": " Studio"," Weekend Gross": " Weekend Gross"," Change": " Change"," Screens / Avg.": " Screens / Avg."," Gross-to-Date": " Gross-to-Date"," Week": " Week","": ""},
"row99": {" TW": "1"," LW": "N"," Movie": "Eat Pray Love"," Studio": "Sony"," Weekend Gross": "$19,142"," Change": "-"," Screens / Avg.": "1"," Gross-to-Date": "$19,142"," Week": "$19,142","": "1"},
"row100": {" TW": "2"," LW": "N"," Movie": "Takers"," Studio": "Sony"," Weekend Gross": "$9,003"," Change": "-"," Screens / Avg.": "1"," Gross-to-Date": "$9,003"," Week": "$9,003","": "1"},
"row101": {" TW": "3"," LW": "2"," Movie": "The Other Guys"," Studio": "Sony"," Weekend Gross": "$3,902"," Change": "-26.4%"," Screens / Avg.": "1"," Gross-to-Date": "$3,902"," Week": "$31,298","": "4"},
"row102": {" TW": "4"," LW": "1"," Movie": "Wall Street: Money Never Sleeps"," Studio": "n/a"," Weekend Gross": "$3,891"," Change": "-47.3%"," Screens / Avg.": "1"," Gross-to-Date": "$3,891"," Week": "$26,800","": "3"},
"row103": {" TW": "5"," LW": "4"," Movie": "Grown Ups"," Studio": "Sony"," Weekend Gross": "$2,125"," Change": "-13.9%"," Screens / Avg.": "1"," Gross-to-Date": "$2,125"," Week": "$73,231","": "10"},
"row104": {" TW": "6"," LW": "3"," Movie": "Salt"," Studio": "Sony"," Weekend Gross": "$2,005"," Change": "-25.7%"," Screens / Avg.": "1"," Gross-to-Date": "$2,005"," Week": "$185,852","": "12"},
"row105": {" TW": "7"," LW": "5"," Movie": "Marmaduke"," Studio": "n/a"," Weekend Gross": "$1,096"," Change": "-37.1%"," Screens / Avg.": "1"," Gross-to-Date": "$1,096"," Week": "$16,338","": "5"},
"row106": {" TW": "8"," LW": "6"," Movie": "Knight & Day"," Studio": "n/a"," Weekend Gross": "$446"," Change": "-55.5%"," Screens / Avg.": "1"," Gross-to-Date": "$446"," Week": "$102,883","": "15"},
"row107": {" TW": "9"," LW": "8"," Movie": "Cyrus"," Studio": "n/a"," Weekend Gross": "$159"," Change": "-61.6%"," Screens / Avg.": "1"," Gross-to-Date": "$159"," Week": "$4,252","": "5"},
"row108": {" TW": " TW"," LW": " LW"," Movie": " Movie"," Studio": " Studio"," Weekend Gross": " Weekend Gross"," Change": " Change"," Screens / Avg.": " Screens / Avg."," Gross-to-Date": " Gross-to-Date"," Week": " Week","": ""},
"row109": {" TW": "1"," LW": "1"," Movie": "Wall Street: Money Never Sleeps"," Studio": "n/a"," Weekend Gross": "$7,388"," Change": "-28.1%"," Screens / Avg.": "1"," Gross-to-Date": "$7,388"," Week": "$22,248","": "2"},
"row110": {" TW": "2"," LW": "2"," Movie": "The Other Guys"," Studio": "Sony"," Weekend Gross": "$5,300"," Change": "-20.6%"," Screens / Avg.": "1"," Gross-to-Date": "$5,300"," Week": "$25,958","": "3"},
"row111": {" TW": "3"," LW": "3"," Movie": "Salt"," Studio": "Sony"," Weekend Gross": "$2,698"," Change": "-14.2%"," Screens / Avg.": "1"," Gross-to-Date": "$2,698"," Week": "$183,130","": "11"},
"row112": {" TW": "4"," LW": "4"," Movie": "Grown Ups"," Studio": "Sony"," Weekend Gross": "$2,467"," Change": "-5.9%"," Screens / Avg.": "1"," Gross-to-Date": "$2,467"," Week": "$70,255","": "9"},
"row113": {" TW": "5"," LW": "5"," Movie": "Marmaduke"," Studio": "n/a"," Weekend Gross": "$1,743"," Change": "+16.5%"," Screens / Avg.": "1"," Gross-to-Date": "$1,743"," Week": "$15,136","": "4"},
"row114": {" TW": "6"," LW": "6"," Movie": "Knight & Day"," Studio": "n/a"," Weekend Gross": "$1,003"," Change": "-25.9%"," Screens / Avg.": "1"," Gross-to-Date": "$1,003"," Week": "$102,199","": "14"},
"row115": {" TW": "7"," LW": "7"," Movie": "The Karate Kid"," Studio": "Sony"," Weekend Gross": "$541"," Change": "+4.6%"," Screens / Avg.": "1"," Gross-to-Date": "$541"," Week": "$151,349","": "16"},
"row116": {" TW": "8"," LW": "9"," Movie": "Cyrus"," Studio": "n/a"," Weekend Gross": "$414"," Change": "-"," Screens / Avg.": "1"," Gross-to-Date": "$414"," Week": "$4,053","": "4"},
"row117": {" TW": "9"," LW": "8"," Movie": "Predators"," Studio": "n/a"," Weekend Gross": "$223"," Change": "-47.2%"," Screens / Avg.": "1"," Gross-to-Date": "$223"," Week": "$33,466","": "10"},
"row118": {" TW": " TW"," LW": " LW"," Movie": " Movie"," Studio": " Studio"," Weekend Gross": " Weekend Gross"," Change": " Change"," Screens / Avg.": " Screens / Avg."," Gross-to-Date": " Gross-to-Date"," Week": " Week","": ""},
"row119": {" TW": "1"," LW": "N"," Movie": "Wall Street: Money Never Sleeps"," Studio": "n/a"," Weekend Gross": "$10,273"," Change": "-"," Screens / Avg.": "1"," Gross-to-Date": "$10,273"," Week": "$13,008","": "1"},
"row120": {" TW": "2"," LW": "1"," Movie": "The Other Guys"," Studio": "Sony"," Weekend Gross": "$6,676"," Change": "-27.3%"," Screens / Avg.": "1"," Gross-to-Date": "$6,676"," Week": "$19,310","": "2"},
"row121": {" TW": "3"," LW": "2"," Movie": "Salt"," Studio": "Sony"," Weekend Gross": "$3,143"," Change": "-34.2%"," Screens / Avg.": "1"," Gross-to-Date": "$3,143"," Week": "$179,279","": "10"},
"row122": {" TW": "4"," LW": "3"," Movie": "Grown Ups"," Studio": "Sony"," Weekend Gross": "$2,621"," Change": "+12.0%"," Screens / Avg.": "1"," Gross-to-Date": "$2,621"," Week": "$67,109","": "8"},
"row123": {" TW": "5"," LW": "4"," Movie": "Marmaduke"," Studio": "n/a"," Weekend Gross": "$1,496"," Change": "-22.3%"," Screens / Avg.": "1"," Gross-to-Date": "$1,496"," Week": "$13,162","": "3"},
"row124": {" TW": "6"," LW": "5"," Movie": "Knight & Day"," Studio": "n/a"," Weekend Gross": "$1,353"," Change": "-14.2%"," Screens / Avg.": "1"," Gross-to-Date": "$1,353"," Week": "$100,817","": "13"},
"row125": {" TW": "7"," LW": "6"," Movie": "The Karate Kid"," Studio": "Sony"," Weekend Gross": "$517"," Change": "-37.6%"," Screens / Avg.": "1"," Gross-to-Date": "$517"," Week": "$150,672","": "15"},
"row126": {" TW": "8"," LW": "7"," Movie": "Predators"," Studio": "n/a"," Weekend Gross": "$422"," Change": "-34.6%"," Screens / Avg.": "1"," Gross-to-Date": "$422"," Week": "$33,130","": "9"},
"row127": {" TW": "9"," LW": "8"," Movie": "Cyrus"," Studio": "n/a"," Weekend Gross": "$414"," Change": "+40.8%"," Screens / Avg.": "1"," Gross-to-Date": "$414"," Week": "$3,480","": "3"},
"row128": {" TW": " TW"," LW": " LW"," Movie": " Movie"," Studio": " Studio"," Weekend Gross": " Weekend Gross"," Change": " Change"," Screens / Avg.": " Screens / Avg."," Gross-to-Date": " Gross-to-Date"," Week": " Week","": ""},
"row129": {" TW": "1"," LW": "N"," Movie": "The Other Guys"," Studio": "Sony"," Weekend Gross": "$9,186"," Change": "-"," Screens / Avg.": "1"," Gross-to-Date": "$9,186"," Week": "$9,186","": "1"},
"row130": {" TW": "2"," LW": "1"," Movie": "Salt"," Studio": "Sony"," Weekend Gross": "$4,777"," Change": "-60.9%"," Screens / Avg.": "1"," Gross-to-Date": "$4,777"," Week": "$173,798","": "9"},
"row131": {" TW": "3"," LW": "2"," Movie": "Grown Ups"," Studio": "Sony"," Weekend Gross": "$2,340"," Change": "-75.8%"," Screens / Avg.": "1"," Gross-to-Date": "$2,340"," Week": "$62,897","": "7"},
"row132": {" TW": "4"," LW": "3"," Movie": "Marmaduke"," Studio": "n/a"," Weekend Gross": "$1,926"," Change": "-68.0%"," Screens / Avg.": "1"," Gross-to-Date": "$1,926"," Week": "$11,387","": "2"},
"row133": {" TW": "5"," LW": "6"," Movie": "Knight & Day"," Studio": "n/a"," Weekend Gross": "$1,576"," Change": "-60.6%"," Screens / Avg.": "1"," Gross-to-Date": "$1,576"," Week": "$99,011","": "12"},
"row134": {" TW": "6"," LW": "4"," Movie": "The Karate Kid"," Studio": "Sony"," Weekend Gross": "$828"," Change": "-84.5%"," Screens / Avg.": "1"," Gross-to-Date": "$828"," Week": "$149,614","": "14"},
"row135": {" TW": "7"," LW": "5"," Movie": "Predators"," Studio": "n/a"," Weekend Gross": "$645"," Change": "-85.6%"," Screens / Avg.": "1"," Gross-to-Date": "$645"," Week": "$32,533","": "8"},
"row136": {" TW": "8"," LW": "7"," Movie": "Cyrus"," Studio": "n/a"," Weekend Gross": "$294"," Change": "-75.7%"," Screens / Avg.": "1"," Gross-to-Date": "$294"," Week": "$2,955","": "2"},
"row137": {" TW": " TW"," LW": " LW"," Movie": " Movie"," Studio": " Studio"," Weekend Gross": " Weekend Gross"," Change": " Change"," Screens / Avg.": " Screens / Avg."," Gross-to-Date": " Gross-to-Date"," Week": " Week","": ""},
"row138": {" TW": "1"," LW": "1"," Movie": "Salt"," Studio": "Sony"," Weekend Gross": "$12,228"," Change": "+231.9%"," Screens / Avg.": "1"," Gross-to-Date": "$12,228"," Week": "$161,623","": "8"},
"row139": {" TW": "2"," LW": "2"," Movie": "Grown Ups"," Studio": "Sony"," Weekend Gross": "$9,660"," Change": "+318.2%"," Screens / Avg.": "1"," Gross-to-Date": "$9,660"," Week": "$55,759","": "6"},
"row140": {" TW": "3"," LW": "N"," Movie": "Marmaduke"," Studio": "n/a"," Weekend Gross": "$6,024"," Change": "-"," Screens / Avg.": "1"," Gross-to-Date": "$6,024"," Week": "$8,873","": "1"},
"row141": {" TW": "4"," LW": "5"," Movie": "The Karate Kid"," Studio": "Sony"," Weekend Gross": "$5,324"," Change": "+627.3%"," Screens / Avg.": "1"," Gross-to-Date": "$5,324"," Week": "$146,081","": "13"},
"row142": {" TW": "5"," LW": "4"," Movie": "Predators"," Studio": "n/a"," Weekend Gross": "$4,469"," Change": "+313.0%"," Screens / Avg.": "1"," Gross-to-Date": "$4,469"," Week": "$31,618","": "7"},
"row143": {" TW": "6"," LW": "3"," Movie": "Knight & Day"," Studio": "n/a"," Weekend Gross": "$3,997"," Change": "+266.7%"," Screens / Avg.": "1"," Gross-to-Date": "$3,997"," Week": "$96,639","": "11"},
"row144": {" TW": "7"," LW": "N"," Movie": "Cyrus"," Studio": "n/a"," Weekend Gross": "$1,212"," Change": "-"," Screens / Avg.": "1"," Gross-to-Date": "$1,212"," Week": "$2,557","": "1"},
"row145": {" TW": "8"," LW": "7"," Movie": "The A-Team"," Studio": "n/a"," Weekend Gross": "$995"," Change": "+74.6%"," Screens / Avg.": "1"," Gross-to-Date": "$995"," Week": "$49,676","": "14"},
"row146": {" TW": "9"," LW": "6"," Movie": "Death at a Funeral (2010)"," Studio": "Sony"," Weekend Gross": "$764"," Change": "+15.8%"," Screens / Avg.": "1"," Gross-to-Date": "$764"," Week": "$36,648","": "15"},
"row147": {" TW": " TW"," LW": " LW"," Movie": " Movie"," Studio": " Studio"," Weekend Gross": " Weekend Gross"," Change": " Change"," Screens / Avg.": " Screens / Avg."," Gross-to-Date": " Gross-to-Date"," Week": " Week","": ""},
"row148": {" TW": "1"," LW": "1"," Movie": "Salt"," Studio": "Sony"," Weekend Gross": "$3,684"," Change": "-31.1%"," Screens / Avg.": "1"," Gross-to-Date": "$3,684"," Week": "$147,716","": "7"},
"row149": {" TW": "2"," LW": "2"," Movie": "Grown Ups"," Studio": "Sony"," Weekend Gross": "$2,310"," Change": "-37.6%"," Screens / Avg.": "1"," Gross-to-Date": "$2,310"," Week": "$44,769","": "5"},
"row150": {" TW": "3"," LW": "5"," Movie": "Knight & Day"," Studio": "n/a"," Weekend Gross": "$1,090"," Change": "+13.2%"," Screens / Avg.": "1"," Gross-to-Date": "$1,090"," Week": "$89,772","": "10"},
"row151": {" TW": "4"," LW": "3"," Movie": "Predators"," Studio": "n/a"," Weekend Gross": "$1,082"," Change": "-13.2%"," Screens / Avg.": "1"," Gross-to-Date": "$1,082"," Week": "$25,244","": "6"},
"row152": {" TW": "5"," LW": "4"," Movie": "The Karate Kid"," Studio": "Sony"," Weekend Gross": "$732"," Change": "-37.0%"," Screens / Avg.": "1"," Gross-to-Date": "$732"," Week": "$140,224","": "12"},
"row153": {" TW": "6"," LW": "6"," Movie": "Death at a Funeral (2010)"," Studio": "Sony"," Weekend Gross": "$660"," Change": "-5.7%"," Screens / Avg.": "1"," Gross-to-Date": "$660"," Week": "$35,637","": "14"},
"row154": {" TW": "7"," LW": "7"," Movie": "The A-Team"," Studio": "n/a"," Weekend Gross": "$570"," Change": "-3.7%"," Screens / Avg.": "1"," Gross-to-Date": "$570"," Week": "$48,244","": "13"},
"row155": {" TW": "8"," LW": "8"," Movie": "The Back-Up Plan"," Studio": "Sony"," Weekend Gross": "$183"," Change": "-54.0%"," Screens / Avg.": "1"," Gross-to-Date": "$183"," Week": "$51,338","": "18"},
"row156": {" TW": " TW"," LW": " LW"," Movie": " Movie"," Studio": " Studio"," Weekend Gross": " Weekend Gross"," Change": " Change"," Screens / Avg.": " Screens / Avg."," Gross-to-Date": " Gross-to-Date"," Week": " Week","": ""},
"row157": {" TW": "1"," LW": "1"," Movie": "Salt"," Studio": "Sony"," Weekend Gross": "$5,347"," Change": "-17.0%"," Screens / Avg.": "1"," Gross-to-Date": "$5,347"," Week": "$142,316","": "6"},
"row158": {" TW": "2"," LW": "2"," Movie": "Grown Ups"," Studio": "Sony"," Weekend Gross": "$3,700"," Change": "-9.2%"," Screens / Avg.": "1"," Gross-to-Date": "$3,700"," Week": "$41,225","": "4"},
"row159": {" TW": "3"," LW": "3"," Movie": "Predators"," Studio": "n/a"," Weekend Gross": "$1,247"," Change": "-5.4%"," Screens / Avg.": "1"," Gross-to-Date": "$1,247"," Week": "$23,817","": "5"},
"row160": {" TW": "4"," LW": "4"," Movie": "The Karate Kid"," Studio": "Sony"," Weekend Gross": "$1,162"," Change": "-6.4%"," Screens / Avg.": "1"," Gross-to-Date": "$1,162"," Week": "$139,222","": "11"},
"row161": {" TW": "5"," LW": "5"," Movie": "Knight & Day"," Studio": "n/a"," Weekend Gross": "$963"," Change": "-18.8%"," Screens / Avg.": "1"," Gross-to-Date": "$963"," Week": "$88,220","": "9"},
"row162": {" TW": "6"," LW": "6"," Movie": "Death at a Funeral (2010)"," Studio": "Sony"," Weekend Gross": "$700"," Change": "+104.7%"," Screens / Avg.": "1"," Gross-to-Date": "$700"," Week": "$34,770","": "13"},
"row163": {" TW": "7"," LW": "9"," Movie": "The A-Team"," Studio": "n/a"," Weekend Gross": "$592"," Change": "+957.1%"," Screens / Avg.": "1"," Gross-to-Date": "$592"," Week": "$47,499","": "12"},
"row164": {" TW": "8"," LW": "8"," Movie": "The Back-Up Plan"," Studio": "Sony"," Weekend Gross": "$398"," Change": "+100.0%"," Screens / Avg.": "1"," Gross-to-Date": "$398"," Week": "$51,012","": "17"},
"row165": {" TW": " TW"," LW": " LW"," Movie": " Movie"," Studio": " Studio"," Weekend Gross": " Weekend Gross"," Change": " Change"," Screens / Avg.": " Screens / Avg."," Gross-to-Date": " Gross-to-Date"," Week": " Week","": ""},
"row166": {" TW": "1"," LW": "1"," Movie": "Salt"," Studio": "Sony"," Weekend Gross": "$6,440"," Change": "-3.6%"," Screens / Avg.": "1"," Gross-to-Date": "$6,440"," Week": "$134,488","": "5"},
"row167": {" TW": "2"," LW": "2"," Movie": "Grown Ups"," Studio": "Sony"," Weekend Gross": "$4,074"," Change": "-10.7%"," Screens / Avg.": "1"," Gross-to-Date": "$4,074"," Week": "$36,135","": "3"},
"row168": {" TW": "3"," LW": "3"," Movie": "Predators"," Studio": "n/a"," Weekend Gross": "$1,318"," Change": "-23.6%"," Screens / Avg.": "1"," Gross-to-Date": "$1,318"," Week": "$22,034","": "4"},
"row169": {" TW": "4"," LW": "4"," Movie": "The Karate Kid"," Studio": "Sony"," Weekend Gross": "$1,241"," Change": "+7.5%"," Screens / Avg.": "1"," Gross-to-Date": "$1,241"," Week": "$137,829","": "10"},
"row170": {" TW": "5"," LW": "5"," Movie": "Knight & Day"," Studio": "n/a"," Weekend Gross": "$1,186"," Change": "+16.4%"," Screens / Avg.": "1"," Gross-to-Date": "$1,186"," Week": "$86,692","": "8"},
"row171": {" TW": "6"," LW": "7"," Movie": "Death at a Funeral (2010)"," Studio": "Sony"," Weekend Gross": "$342"," Change": "+30.0%"," Screens / Avg.": "1"," Gross-to-Date": "$342"," Week": "$33,974","": "12"},
"row172": {" TW": "7"," LW": "8"," Movie": "Date Night"," Studio": "n/a"," Weekend Gross": "$215"," Change": "+93.7%"," Screens / Avg.": "1"," Gross-to-Date": "$215"," Week": "$60,058","": "20"},
"row173": {" TW": "8"," LW": "9"," Movie": "The Back-Up Plan"," Studio": "Sony"," Weekend Gross": "$199"," Change": "+93.2%"," Screens / Avg.": "1"," Gross-to-Date": "$199"," Week": "$50,542","": "16"},
"row174": {" TW": "9"," LW": "6"," Movie": "The A-Team"," Studio": "n/a"," Weekend Gross": "$56"," Change": "-87.8%"," Screens / Avg.": "1"," Gross-to-Date": "$56"," Week": "$46,634","": "11"},
"row175": {" TW": " TW"," LW": " LW"," Movie": " Movie"," Studio": " Studio"," Weekend Gross": " Weekend Gross"," Change": " Change"," Screens / Avg.": " Screens"," Gross-to-Date": " Change / Avg."," Week": " Gross-to-Date","": " Week"},
"row176": {" TW": "1"," LW": "1"," Movie": "Salt"," Studio": "Sony"," Weekend Gross": "$6,682"," Change": "-76.8%"," Screens / Avg.": "1"," Gross-to-Date": "-1"," Week": "$6,682","": "$124,695"},
"row177": {" TW": "2"," LW": "2"," Movie": "Grown Ups"," Studio": "Sony"," Weekend Gross": "$4,562"," Change": "-77.2%"," Screens / Avg.": "1"," Gross-to-Date": "-"," Week": "$4,562","": "$29,560"},
"row178": {" TW": "3"," LW": "4"," Movie": "Predators"," Studio": "n/a"," Weekend Gross": "$1,724"," Change": "-67.1%"," Screens / Avg.": "1"," Gross-to-Date": "-1"," Week": "$1,724","": "$20,207"},
"row179": {" TW": "4"," LW": "3"," Movie": "The Karate Kid"," Studio": "Sony"," Weekend Gross": "$1,154"," Change": "-79.8%"," Screens / Avg.": "1"," Gross-to-Date": "-1"," Week": "$1,154","": "$135,935"},
"row180": {" TW": "5"," LW": "5"," Movie": "Knight & Day"," Studio": "n/a"," Weekend Gross": "$1,019"," Change": "-75.8%"," Screens / Avg.": "1"," Gross-to-Date": "-"," Week": "$1,019","": "$85,085"},
"row181": {" TW": "6"," LW": "6"," Movie": "The A-Team"," Studio": "n/a"," Weekend Gross": "$459"," Change": "-79.8%"," Screens / Avg.": "1"," Gross-to-Date": "-"," Week": "$459","": "$45,809"},
"row182": {" TW": "7"," LW": "7"," Movie": "Death at a Funeral (2010)"," Studio": "Sony"," Weekend Gross": "$263"," Change": "-72.7%"," Screens / Avg.": "1"," Gross-to-Date": "-"," Week": "$263","": "$33,528"},
"row183": {" TW": "8"," LW": "9"," Movie": "Date Night"," Studio": "n/a"," Weekend Gross": "$111"," Change": "-76.7%"," Screens / Avg.": "1"," Gross-to-Date": "-"," Week": "$111","": "$59,788"},
"row184": {" TW": "9"," LW": "8"," Movie": "The Back-Up Plan"," Studio": "Sony"," Weekend Gross": "$103"," Change": "-84.8%"," Screens / Avg.": "1"," Gross-to-Date": "-"," Week": "$103","": "$50,311"},
"row185": {" TW": " TW"," LW": " LW"," Movie": " Movie"," Studio": " Studio"," Weekend Gross": " Weekend Gross"," Change": " Change"," Screens / Avg.": " Screens"," Gross-to-Date": " Change / Avg."," Week": " Gross-to-Date","": " Week"},
"row186": {" TW": "1"," LW": "1"," Movie": "Salt"," Studio": "Sony"," Weekend Gross": "$28,759"," Change": "-4.2%"," Screens / Avg.": "2"," Gross-to-Date": "-"," Week": "$14,380","": "$110,721"},
"row187": {" TW": "2"," LW": "N"," Movie": "Grown Ups"," Studio": "Sony"," Weekend Gross": "$20,032"," Change": "-"," Screens / Avg.": "1"," Gross-to-Date": "-"," Week": "$20,032","": "$20,032"},
"row188": {" TW": "3"," LW": "3"," Movie": "The Karate Kid"," Studio": "Sony"," Weekend Gross": "$5,721"," Change": "-16.7%"," Screens / Avg.": "2"," Gross-to-Date": "-"," Week": "$2,861","": "$133,460"},
"row189": {" TW": "4"," LW": "2"," Movie": "Predators"," Studio": "n/a"," Weekend Gross": "$5,233"," Change": "-37.5%"," Screens / Avg.": "2"," Gross-to-Date": "-"," Week": "$2,617","": "$18,021"},
"row190": {" TW": "5"," LW": "4"," Movie": "Knight & Day"," Studio": "n/a"," Weekend Gross": "$4,210"," Change": "-23.8%"," Screens / Avg.": "1"," Gross-to-Date": "-1"," Week": "$4,210","": "$83,565"},
"row191": {" TW": "6"," LW": "5"," Movie": "The A-Team"," Studio": "n/a"," Weekend Gross": "$2,271"," Change": "+1.7%"," Screens / Avg.": "1"," Gross-to-Date": "-"," Week": "$2,271","": "$45,239"},
"row192": {" TW": "7"," LW": "6"," Movie": "Death at a Funeral (2010)"," Studio": "Sony"," Weekend Gross": "$963"," Change": "-20.4%"," Screens / Avg.": "1"," Gross-to-Date": "-"," Week": "$963","": "$33,099"},
"row193": {" TW": "8"," LW": "8"," Movie": "The Back-Up Plan"," Studio": "Sony"," Weekend Gross": "$676"," Change": "+7.5%"," Screens / Avg.": "1"," Gross-to-Date": "-"," Week": "$676","": "$50,073"},
"row194": {" TW": "9"," LW": "7"," Movie": "Date Night"," Studio": "n/a"," Weekend Gross": "$477"," Change": "-28.6%"," Screens / Avg.": "1"," Gross-to-Date": "-"," Week": "$477","": "$59,565"},
"row195": {" TW": " TW"," LW": " LW"," Movie": " Movie"," Studio": " Studio"," Weekend Gross": " Weekend Gross"," Change": " Change"," Screens / Avg.": " Screens"," Gross-to-Date": " Change / Avg."," Week": " Gross-to-Date","": " Week"},
"row196": {" TW": "1"," LW": "1"," Movie": "Salt"," Studio": "Sony"," Weekend Gross": "$30,013"," Change": "+13.0%"," Screens / Avg.": "2"," Gross-to-Date": "-"," Week": "$15,007","": "$69,345"},
"row197": {" TW": "2"," LW": "N"," Movie": "Predators"," Studio": "n/a"," Weekend Gross": "$8,374"," Change": "-"," Screens / Avg.": "2"," Gross-to-Date": "-"," Week": "$4,187","": "$11,408"},
"row198": {" TW": "3"," LW": "2"," Movie": "The Karate Kid"," Studio": "Sony"," Weekend Gross": "$6,867"," Change": "-5.5%"," Screens / Avg.": "2"," Gross-to-Date": "+1"," Week": "$3,434","": "$124,277"},
"row199": {" TW": "4"," LW": "3"," Movie": "Knight & Day"," Studio": "n/a"," Weekend Gross": "$5,523"," Change": "-23.5%"," Screens / Avg.": "2"," Gross-to-Date": "-"," Week": "$2,762","": "$77,939"},
"row200": {" TW": "5"," LW": "4"," Movie": "The A-Team"," Studio": "n/a"," Weekend Gross": "$2,233"," Change": "-2.9%"," Screens / Avg.": "1"," Gross-to-Date": "-"," Week": "$2,233","": "$42,218"},
"row201": {" TW": "6"," LW": "5"," Movie": "Death at a Funeral (2010)"," Studio": "Sony"," Weekend Gross": "$1,210"," Change": "+8.3%"," Screens / Avg.": "1"," Gross-to-Date": "-"," Week": "$1,210","": "$31,404"},
"row202": {" TW": "7"," LW": "7"," Movie": "Date Night"," Studio": "n/a"," Weekend Gross": "$668"," Change": "+42.4%"," Screens / Avg.": "1"," Gross-to-Date": "-"," Week": "$668","": "$58,936"},
"row203": {" TW": "8"," LW": "6"," Movie": "The Back-Up Plan"," Studio": "Sony"," Weekend Gross": "$629"," Change": "+11.3%"," Screens / Avg.": "1"," Gross-to-Date": "-"," Week": "$629","": "$49,054"},
"row204": {" TW": " TW"," LW": " LW"," Movie": " Movie"," Studio": " Studio"," Weekend Gross": " Weekend Gross"," Change": " Change"," Screens / Avg.": " Screens"," Gross-to-Date": " Change / Avg."," Week": " Gross-to-Date","": " Week"},
"row205": {" TW": "1"," LW": "N"," Movie": "Salt"," Studio": "Sony"," Weekend Gross": "$26,562"," Change": "-"," Screens / Avg.": "2"," Gross-to-Date": "-"," Week": "$13,281","": "$26,562"},
"row206": {" TW": "2"," LW": "2"," Movie": "The Karate Kid"," Studio": "Sony"," Weekend Gross": "$7,265"," Change": "-38.2%"," Screens / Avg.": "1"," Gross-to-Date": "-1"," Week": "$7,265","": "$114,855"},
"row207": {" TW": "3"," LW": "1"," Movie": "Knight & Day"," Studio": "n/a"," Weekend Gross": "$7,218"," Change": "-39.2%"," Screens / Avg.": "2"," Gross-to-Date": "+1"," Week": "$3,609","": "$69,719"},
"row208": {" TW": "4"," LW": "3"," Movie": "The A-Team"," Studio": "n/a"," Weekend Gross": "$2,300"," Change": "-23.1%"," Screens / Avg.": "1"," Gross-to-Date": "-"," Week": "$2,300","": "$38,851"},
"row209": {" TW": "5"," LW": "5"," Movie": "Death at a Funeral (2010)"," Studio": "Sony"," Weekend Gross": "$1,117"," Change": "+12.3%"," Screens / Avg.": "1"," Gross-to-Date": "-"," Week": "$1,117","": "$29,412"},
"row210": {" TW": "6"," LW": "4"," Movie": "The Back-Up Plan"," Studio": "Sony"," Weekend Gross": "$565"," Change": "-46.2%"," Screens / Avg.": "1"," Gross-to-Date": "-"," Week": "$565","": "$47,908"},
"row211": {" TW": "7"," LW": "6"," Movie": "Date Night"," Studio": "n/a"," Weekend Gross": "$469"," Change": "+9.1%"," Screens / Avg.": "1"," Gross-to-Date": "-"," Week": "$469","": "$57,830"},
"row212": {" TW": " TW"," LW": " LW"," Movie": " Movie"," Studio": " Studio"," Weekend Gross": " Weekend Gross"," Change": " Change"," Screens / Avg.": " Screens"," Gross-to-Date": " Change / Avg."," Week": " Gross-to-Date","": " Week"},
"row213": {" TW": "1"," LW": "1"," Movie": "Knight & Day"," Studio": "n/a"," Weekend Gross": "$11,873"," Change": "-27.4%"," Screens / Avg.": "1"," Gross-to-Date": "-1"," Week": "$11,873","": "$59,692"},
"row214": {" TW": "2"," LW": "2"," Movie": "The Karate Kid"," Studio": "Sony"," Weekend Gross": "$11,761"," Change": "-8.4%"," Screens / Avg.": "2"," Gross-to-Date": "-"," Week": "$5,881","": "$103,325"},
"row215": {" TW": "3"," LW": "3"," Movie": "The A-Team"," Studio": "n/a"," Weekend Gross": "$2,992"," Change": "-23.7%"," Screens / Avg.": "1"," Gross-to-Date": "-"," Week": "$2,992","": "$35,310"},
"row216": {" TW": "4"," LW": "5"," Movie": "The Back-Up Plan"," Studio": "Sony"," Weekend Gross": "$1,050"," Change": "-8.0%"," Screens / Avg.": "1"," Gross-to-Date": "-"," Week": "$1,050","": "$46,911"},
"row217": {" TW": "5"," LW": "4"," Movie": "Death at a Funeral (2010)"," Studio": "Sony"," Weekend Gross": "$995"," Change": "-20.3%"," Screens / Avg.": "1"," Gross-to-Date": "-"," Week": "$995","": "$27,698"},
"row218": {" TW": "6"," LW": "7"," Movie": "Date Night"," Studio": "n/a"," Weekend Gross": "$430"," Change": "-41.3%"," Screens / Avg.": "1"," Gross-to-Date": "-"," Week": "$430","": "$57,098"},
"row219": {" TW": "7"," LW": "8"," Movie": "Alvin and the Chipmunks: The Squeakquel"," Studio": "n/a"," Weekend Gross": "$271"," Change": "-47.6%"," Screens / Avg.": "1"," Gross-to-Date": "-"," Week": "$271","": "$131,602"},
"row220": {" TW": " TW"," LW": " LW"," Movie": " Movie"," Studio": " Studio"," Weekend Gross": " Weekend Gross"," Change": " Change"," Screens / Avg.": " Screens / Avg."," Gross-to-Date": " Gross-to-Date"," Week": " Week","": ""},
"row221": {" TW": "1"," LW": "1"," Movie": "Knight & Day"," Studio": "n/a"," Weekend Gross": "$16,353"," Change": "-1.0%"," Screens / Avg.": "2"," Gross-to-Date": "$8,177"," Week": "$44,302","": "2"},
"row222": {" TW": "2"," LW": "2"," Movie": "The Karate Kid"," Studio": "Sony"," Weekend Gross": "$12,836"," Change": "-20.1%"," Screens / Avg.": "2"," Gross-to-Date": "$6,418"," Week": "$86,455","": "4"},
"row223": {" TW": "3"," LW": "3"," Movie": "The A-Team"," Studio": "n/a"," Weekend Gross": "$3,923"," Change": "+11.8%"," Screens / Avg.": "1"," Gross-to-Date": "$3,923"," Week": "$30,496","": "5"},
"row224": {" TW": "4"," LW": "5"," Movie": "Death at a Funeral (2010)"," Studio": "Sony"," Weekend Gross": "$1,249"," Change": "+18.1%"," Screens / Avg.": "1"," Gross-to-Date": "$1,249"," Week": "$25,932","": "6"},
"row225": {" TW": "5"," LW": "4"," Movie": "The Back-Up Plan"," Studio": "Sony"," Weekend Gross": "$1,141"," Change": "-27.0%"," Screens / Avg.": "1"," Gross-to-Date": "$1,141"," Week": "$45,232","": "10"},
"row226": {" TW": "6"," LW": "7"," Movie": "Avatar"," Studio": "Fox"," Weekend Gross": "$1,098"," Change": "+119.2%"," Screens / Avg.": "1"," Gross-to-Date": "$1,098"," Week": "$896,623","": "30"},
"row227": {" TW": "7"," LW": "6"," Movie": "Date Night"," Studio": "n/a"," Weekend Gross": "$732"," Change": "+41.6%"," Screens / Avg.": "1"," Gross-to-Date": "$732"," Week": "$56,509","": "14"},
"row228": {" TW": "8"," LW": "8"," Movie": "Alvin and the Chipmunks: The Squeakquel"," Studio": "n/a"," Weekend Gross": "$517"," Change": "+24.9%"," Screens / Avg.": "1"," Gross-to-Date": "$517"," Week": "$131,093","": "28"},
"row229": {" TW": " TW"," LW": " LW"," Movie": " Movie"," Studio": " Studio"," Weekend Gross": " Weekend Gross"," Change": " Change"," Screens / Avg.": " Screens"," Gross-to-Date": " Change / Avg."," Week": " Gross-to-Date","": " Week"},
"row230": {" TW": "1"," LW": "N"," Movie": "Knight & Day"," Studio": "n/a"," Weekend Gross": "$16,523"," Change": "-"," Screens / Avg.": "2"," Gross-to-Date": "-"," Week": "$8,262","": "$21,820"},
"row231": {" TW": "2"," LW": "1"," Movie": "The Karate Kid"," Studio": "Sony"," Weekend Gross": "$16,058"," Change": "-25.5%"," Screens / Avg.": "2"," Gross-to-Date": "+1"," Week": "$8,029","": "$68,280"},
"row232": {" TW": "3"," LW": "2"," Movie": "The A-Team"," Studio": "n/a"," Weekend Gross": "$3,509"," Change": "-26.5%"," Screens / Avg.": "1"," Gross-to-Date": "-"," Week": "$3,509","": "$25,061"},
"row233": {" TW": "4"," LW": "4"," Movie": "The Back-Up Plan"," Studio": "Sony"," Weekend Gross": "$1,562"," Change": "+12.1%"," Screens / Avg.": "1"," Gross-to-Date": "-"," Week": "$1,562","": "$43,725"},
"row234": {" TW": "5"," LW": "3"," Movie": "Death at a Funeral (2010)"," Studio": "Sony"," Weekend Gross": "$1,058"," Change": "-67.6%"," Screens / Avg.": "1"," Gross-to-Date": "-"," Week": "$1,058","": "$24,245"},
"row235": {" TW": "6"," LW": "5"," Movie": "Date Night"," Studio": "n/a"," Weekend Gross": "$517"," Change": "-61.6%"," Screens / Avg.": "1"," Gross-to-Date": "-"," Week": "$517","": "$55,491"},
"row236": {" TW": "7"," LW": "6"," Movie": "Avatar"," Studio": "Fox"," Weekend Gross": "$501"," Change": "-4.6%"," Screens / Avg.": "1"," Gross-to-Date": "-"," Week": "$501","": "$894,968"},
"row237": {" TW": "8"," LW": "7"," Movie": "Alvin and the Chipmunks: The Squeakquel"," Studio": "n/a"," Weekend Gross": "$414"," Change": "-19.9%"," Screens / Avg.": "1"," Gross-to-Date": "-"," Week": "$414","": "$130,210"},
"row238": {" TW": " TW"," LW": " LW"," Movie": " Movie"," Studio": " Studio"," Weekend Gross": " Weekend Gross"," Change": " Change"," Screens / Avg.": " Screens"," Gross-to-Date": " Change / Avg."," Week": " Gross-to-Date","": " Week"},
"row239": {" TW": "1"," LW": "1"," Movie": "The Karate Kid"," Studio": "Sony"," Weekend Gross": "$21,552"," Change": "+31.7%"," Screens / Avg.": "1"," Gross-to-Date": "-1"," Week": "$21,552","": "$44,757"},
"row240": {" TW": "2"," LW": "2"," Movie": "The A-Team"," Studio": "n/a"," Weekend Gross": "$4,775"," Change": "+27.4%"," Screens / Avg.": "1"," Gross-to-Date": "-"," Week": "$4,775","": "$20,573"},
"row241": {" TW": "3"," LW": "3"," Movie": "Death at a Funeral (2010)"," Studio": "Sony"," Weekend Gross": "$3,263"," Change": "+11.7%"," Screens / Avg.": "1"," Gross-to-Date": "-"," Week": "$3,263","": "$21,531"},
"row242": {" TW": "4"," LW": "4"," Movie": "The Back-Up Plan"," Studio": "Sony"," Weekend Gross": "$1,393"," Change": "-3.1%"," Screens / Avg.": "1"," Gross-to-Date": "-"," Week": "$1,393","": "$41,569"},
"row243": {" TW": "5"," LW": "5"," Movie": "Date Night"," Studio": "n/a"," Weekend Gross": "$1,345"," Change": "-1.8%"," Screens / Avg.": "1"," Gross-to-Date": "-"," Week": "$1,345","": "$54,673"},
"row244": {" TW": "6"," LW": "6"," Movie": "Avatar"," Studio": "Fox"," Weekend Gross": "$525"," Change": "-"," Screens / Avg.": "1"," Gross-to-Date": "-"," Week": "$525","": "$894,371"},
"row245": {" TW": "7"," LW": "7"," Movie": "Alvin and the Chipmunks: The Squeakquel"," Studio": "n/a"," Weekend Gross": "$517"," Change": "+8.4%"," Screens / Avg.": "1"," Gross-to-Date": "-"," Week": "$517","": "$129,648"},
"row246": {" TW": "8"," LW": "8"," Movie": "The Bounty Hunter"," Studio": "Sony"," Weekend Gross": "$414"," Change": "+8.4%"," Screens / Avg.": "1"," Gross-to-Date": "-"," Week": "$414","": "$55,932"},
"row247": {" TW": " TW"," LW": " LW"," Movie": " Movie"," Studio": " Studio"," Weekend Gross": " Weekend Gross"," Change": " Change"," Screens / Avg.": " Screens / Avg."," Gross-to-Date": " Gross-to-Date"," Week": " Week","": ""},
"row248": {" TW": "1"," LW": "N"," Movie": "The Karate Kid"," Studio": "Sony"," Weekend Gross": "$16,364"," Change": "-"," Screens / Avg.": "2"," Gross-to-Date": "$8,182"," Week": "$16,364","": "1"},
"row249": {" TW": "2"," LW": "1"," Movie": "The A-Team"," Studio": "n/a"," Weekend Gross": "$3,748"," Change": "-41.8%"," Screens / Avg.": "1"," Gross-to-Date": "$3,748"," Week": "$14,112","": "2"},
"row250": {" TW": "3"," LW": "2"," Movie": "Death at a Funeral (2010)"," Studio": "Sony"," Weekend Gross": "$2,921"," Change": "-23.4%"," Screens / Avg.": "1"," Gross-to-Date": "$2,921"," Week": "$16,597","": "3"},
"row251": {" TW": "4"," LW": "3"," Movie": "The Back-Up Plan"," Studio": "Sony"," Weekend Gross": "$1,438"," Change": "+0.4%"," Screens / Avg.": "1"," Gross-to-Date": "$1,438"," Week": "$39,415","": "7"},
"row252": {" TW": "5"," LW": "4"," Movie": "Date Night"," Studio": "n/a"," Weekend Gross": "$1,369"," Change": "+10.8%"," Screens / Avg.": "1"," Gross-to-Date": "$1,369"," Week": "$52,460","": "11"},
"row253": {" TW": "6"," LW": "5"," Movie": "Avatar"," Studio": "Fox"," Weekend Gross": "$525"," Change": "-14.4%"," Screens / Avg.": "1"," Gross-to-Date": "$525"," Week": "$893,567","": "27"},
"row254": {" TW": "7"," LW": "8"," Movie": "Alvin and the Chipmunks: The Squeakquel"," Studio": "n/a"," Weekend Gross": "$477"," Change": "+3.3%"," Screens / Avg.": "1"," Gross-to-Date": "$477"," Week": "$128,757","": "25"},
"row255": {" TW": "8"," LW": "7"," Movie": "The Bounty Hunter"," Studio": "Sony"," Weekend Gross": "$382"," Change": "-27.2%"," Screens / Avg.": "1"," Gross-to-Date": "$382"," Week": "$55,367","": "13"},
"row256": {" TW": " TW"," LW": " LW"," Movie": " Movie"," Studio": " Studio"," Weekend Gross": " Weekend Gross"," Change": " Change"," Screens / Avg.": " Screens / Avg."," Gross-to-Date": " Gross-to-Date"," Week": " Week","": ""},
"row257": {" TW": "1"," LW": "N"," Movie": "The A-Team"," Studio": "n/a"," Weekend Gross": "$6,438"," Change": "-"," Screens / Avg.": "1"," Gross-to-Date": "$6,438"," Week": "$8,756","": "1"},
"row258": {" TW": "2"," LW": "1"," Movie": "Death at a Funeral (2010)"," Studio": "Sony"," Weekend Gross": "$3,812"," Change": "-41.3%"," Screens / Avg.": "1"," Gross-to-Date": "$3,812"," Week": "$12,411","": "2"},
"row259": {" TW": "3"," LW": "2"," Movie": "The Back-Up Plan"," Studio": "Sony"," Weekend Gross": "$1,432"," Change": "-31.7%"," Screens / Avg.": "1"," Gross-to-Date": "$1,432"," Week": "$37,364","": "6"},
"row260": {" TW": "4"," LW": "3"," Movie": "Date Night"," Studio": "n/a"," Weekend Gross": "$1,236"," Change": "-9.2%"," Screens / Avg.": "1"," Gross-to-Date": "$1,236"," Week": "$50,718","": "10"},
"row261": {" TW": "5"," LW": "4"," Movie": "Avatar"," Studio": "Fox"," Weekend Gross": "$613"," Change": "-27.4%"," Screens / Avg.": "1"," Gross-to-Date": "$613"," Week": "$892,684","": "26"},
"row262": {" TW": "6"," LW": "8"," Movie": "Tooth Fairy"," Studio": "n/a"," Weekend Gross": "$597"," Change": "+15.5%"," Screens / Avg.": "1"," Gross-to-Date": "$597"," Week": "$30,693","": "11"},
"row263": {" TW": "7"," LW": "6"," Movie": "The Bounty Hunter"," Studio": "Sony"," Weekend Gross": "$525"," Change": "-32.3%"," Screens / Avg.": "1"," Gross-to-Date": "$525"," Week": "$54,842","": "12"},
"row264": {" TW": "8"," LW": "5"," Movie": "Alvin and the Chipmunks: The Squeakquel"," Studio": "n/a"," Weekend Gross": "$462"," Change": "-43.7%"," Screens / Avg.": "1"," Gross-to-Date": "$462"," Week": "$128,136","": "24"},
"row265": {" TW": "9"," LW": "9"," Movie": "Percy Jackson & The Olympians: The Lightning Thief"," Studio": "n/a"," Weekend Gross": "$294"," Change": "-19.7%"," Screens / Avg.": "1"," Gross-to-Date": "$294"," Week": "$45,152","": "16"},
"row266": {" TW": " TW"," LW": " LW"," Movie": " Movie"," Studio": " Studio"," Weekend Gross": " Weekend Gross"," Change": " Change"," Screens / Avg.": " Screens"," Gross-to-Date": " Change / Avg."," Week": " Gross-to-Date","": " Week"},
"row267": {" TW": "1"," LW": "N"," Movie": "Death at a Funeral (2010)"," Studio": "Sony"," Weekend Gross": "$6,491"," Change": "-"," Screens / Avg.": "1"," Gross-to-Date": "-"," Week": "$6,491","": "$6,491"},
"row268": {" TW": "2"," LW": "1"," Movie": "The Back-Up Plan"," Studio": "Sony"," Weekend Gross": "$2,096"," Change": "-45.3%"," Screens / Avg.": "1"," Gross-to-Date": "-"," Week": "$2,096","": "$35,091"},
"row269": {" TW": "3"," LW": "2"," Movie": "Date Night"," Studio": "n/a"," Weekend Gross": "$1,361"," Change": "-38.3%"," Screens / Avg.": "1"," Gross-to-Date": "-"," Week": "$1,361","": "$49,062"},
"row270": {" TW": "4"," LW": "3"," Movie": "Avatar"," Studio": "Fox"," Weekend Gross": "$844"," Change": "-53.1%"," Screens / Avg.": "1"," Gross-to-Date": "-1"," Week": "$844","": "$891,809"},
"row271": {" TW": "5"," LW": "7"," Movie": "Alvin and the Chipmunks: The Squeakquel"," Studio": "n/a"," Weekend Gross": "$820"," Change": "+13.3%"," Screens / Avg.": "1"," Gross-to-Date": "-"," Week": "$820","": "$127,587"},
"row272": {" TW": "6"," LW": "4"," Movie": "The Bounty Hunter"," Studio": "Sony"," Weekend Gross": "$775"," Change": "-41.7%"," Screens / Avg.": "1"," Gross-to-Date": "-"," Week": "$775","": "$53,982"},
"row273": {" TW": "7"," LW": "8"," Movie": "My Name is Khan"," Studio": "n/a"," Weekend Gross": "$621"," Change": "+14.8%"," Screens / Avg.": "1"," Gross-to-Date": "-"," Week": "$621","": "$459,593"},
"row274": {" TW": "8"," LW": "6"," Movie": "Tooth Fairy"," Studio": "n/a"," Weekend Gross": "$517"," Change": "-35.1%"," Screens / Avg.": "1"," Gross-to-Date": "-"," Week": "$517","": "$29,937"},
"row275": {" TW": "9"," LW": "5"," Movie": "Percy Jackson & The Olympians: The Lightning Thief"," Studio": "n/a"," Weekend Gross": "$366"," Change": "-61.0%"," Screens / Avg.": "1"," Gross-to-Date": "-"," Week": "$366","": "$44,747"},
"row276": {" TW": "10"," LW": "9"," Movie": "A Prophet (Un prophte)"," Studio": "n/a"," Weekend Gross": "$231"," Change": "-9.4%"," Screens / Avg.": "1"," Gross-to-Date": "-"," Week": "$231","": "$3,796"},
"row277": {" TW": " TW"," LW": " LW"," Movie": " Movie"," Studio": " Studio"," Weekend Gross": " Weekend Gross"," Change": " Change"," Screens / Avg.": " Screens / Avg."," Gross-to-Date": " Gross-to-Date"," Week": " Week","": ""},
"row278": {" TW": "1"," LW": "1"," Movie": "The Back-Up Plan"," Studio": "Sony"," Weekend Gross": "$3,830"," Change": "-15.1%"," Screens / Avg.": "1"," Gross-to-Date": "$3,830"," Week": "$31,433","": "4"},
"row279": {" TW": "2"," LW": "2"," Movie": "Date Night"," Studio": "n/a"," Weekend Gross": "$2,204"," Change": "-19.0%"," Screens / Avg.": "1"," Gross-to-Date": "$2,204"," Week": "$47,137","": "8"},
"row280": {" TW": "3"," LW": "3"," Movie": "Avatar"," Studio": "Fox"," Weekend Gross": "$1,798"," Change": "-24.0%"," Screens / Avg.": "2"," Gross-to-Date": "$899"," Week": "$890,536","": "24"},
"row281": {" TW": "4"," LW": "4"," Movie": "The Bounty Hunter"," Studio": "Sony"," Weekend Gross": "$1,329"," Change": "-17.0%"," Screens / Avg.": "1"," Gross-to-Date": "$1,329"," Week": "$52,661","": "10"},
"row282": {" TW": "5"," LW": "7"," Movie": "Percy Jackson & The Olympians: The Lightning Thief"," Studio": "n/a"," Weekend Gross": "$939"," Change": "+45.6%"," Screens / Avg.": "1"," Gross-to-Date": "$939"," Week": "$44,253","": "14"},
"row283": {" TW": "6"," LW": "6"," Movie": "Tooth Fairy"," Studio": "n/a"," Weekend Gross": "$796"," Change": "-9.0%"," Screens / Avg.": "1"," Gross-to-Date": "$796"," Week": "$29,316","": "9"},
"row284": {" TW": "7"," LW": "5"," Movie": "Alvin and the Chipmunks: The Squeakquel"," Studio": "n/a"," Weekend Gross": "$724"," Change": "-34.5%"," Screens / Avg.": "1"," Gross-to-Date": "$724"," Week": "$126,640","": "22"},
"row285": {" TW": "8"," LW": "8"," Movie": "My Name is Khan"," Studio": "n/a"," Weekend Gross": "$541"," Change": "-15.1%"," Screens / Avg.": "1"," Gross-to-Date": "$541"," Week": "$458,797","": "15"},
"row286": {" TW": "9"," LW": "9"," Movie": "A Prophet (Un prophte)"," Studio": "n/a"," Weekend Gross": "$255"," Change": "+23.2%"," Screens / Avg.": "1"," Gross-to-Date": "$255"," Week": "$3,454","": "6"},
"row287": {" TW": " TW"," LW": " LW"," Movie": " Movie"," Studio": " Studio"," Weekend Gross": " Weekend Gross"," Change": " Change"," Screens / Avg.": " Screens / Avg."," Gross-to-Date": " Gross-to-Date"," Week": " Week","": ""},
"row288": {" TW": "1"," LW": "1"," Movie": "The Back-Up Plan"," Studio": "Sony"," Weekend Gross": "$4,509"," Change": "-42.6%"," Screens / Avg.": "1"," Gross-to-Date": "$4,509"," Week": "$25,603","": "3"},
"row289": {" TW": "2"," LW": "3"," Movie": "Date Night"," Studio": "n/a"," Weekend Gross": "$2,722"," Change": "+2.4%"," Screens / Avg.": "1"," Gross-to-Date": "$2,722"," Week": "$43,977","": "7"},
"row290": {" TW": "3"," LW": "2"," Movie": "Avatar"," Studio": "Fox"," Weekend Gross": "$2,366"," Change": "-21.3%"," Screens / Avg.": "2"," Gross-to-Date": "$1,183"," Week": "$888,138","": "23"},
"row291": {" TW": "4"," LW": "4"," Movie": "The Bounty Hunter"," Studio": "Sony"," Weekend Gross": "$1,602"," Change": "+20.1%"," Screens / Avg.": "1"," Gross-to-Date": "$1,602"," Week": "$50,791","": "9"},
"row292": {" TW": "5"," LW": "6"," Movie": "Alvin and the Chipmunks: The Squeakquel"," Studio": "n/a"," Weekend Gross": "$1,106"," Change": "+34.9%"," Screens / Avg.": "1"," Gross-to-Date": "$1,106"," Week": "$125,653","": "21"},
"row293": {" TW": "6"," LW": "7"," Movie": "Tooth Fairy"," Studio": "n/a"," Weekend Gross": "$875"," Change": "+31.0%"," Screens / Avg.": "1"," Gross-to-Date": "$875"," Week": "$28,369","": "8"},
"row294": {" TW": "7"," LW": "8"," Movie": "Percy Jackson & The Olympians: The Lightning Thief"," Studio": "n/a"," Weekend Gross": "$645"," Change": "+6.6%"," Screens / Avg.": "1"," Gross-to-Date": "$645"," Week": "$43,131","": "13"},
"row295": {" TW": "8"," LW": "5"," Movie": "My Name is Khan"," Studio": "n/a"," Weekend Gross": "$637"," Change": "-46.7%"," Screens / Avg.": "1"," Gross-to-Date": "$637"," Week": "$458,017","": "14"},
"row296": {" TW": "9"," LW": "10"," Movie": "A Prophet (Un prophte)"," Studio": "n/a"," Weekend Gross": "$207"," Change": "-"," Screens / Avg.": "1"," Gross-to-Date": "$207"," Week": "$3,167","": "5"},
"row297": {" TW": " TW"," LW": " LW"," Movie": " Movie"," Studio": " Studio"," Weekend Gross": " Weekend Gross"," Change": " Change"," Screens / Avg.": " Screens"," Gross-to-Date": " Change / Avg."," Week": " Gross-to-Date","": " Week"},
"row298": {" TW": "1"," LW": "1"," Movie": "The Back-Up Plan"," Studio": "Sony"," Weekend Gross": "$7,849"," Change": "-3.8%"," Screens / Avg.": "1"," Gross-to-Date": "-"," Week": "$7,849","": "$18,698"},
"row299": {" TW": "2"," LW": "3"," Movie": "Avatar"," Studio": "Fox"," Weekend Gross": "$3,005"," Change": "+10.4%"," Screens / Avg.": "2"," Gross-to-Date": "+1"," Week": "$1,503","": "$884,819"},
"row300": {" TW": "3"," LW": "2"," Movie": "Date Night"," Studio": "n/a"," Weekend Gross": "$2,658"," Change": "-21.4%"," Screens / Avg.": "1"," Gross-to-Date": "-"," Week": "$2,658","": "$40,436"},
"row301": {" TW": "4"," LW": "4"," Movie": "The Bounty Hunter"," Studio": "Sony"," Weekend Gross": "$1,334"," Change": "-25.2%"," Screens / Avg.": "1"," Gross-to-Date": "-"," Week": "$1,334","": "$48,674"},
"row302": {" TW": "5"," LW": "5"," Movie": "My Name is Khan"," Studio": "n/a"," Weekend Gross": "$1,194"," Change": "+0.7%"," Screens / Avg.": "1"," Gross-to-Date": "-"," Week": "$1,194","": "$457,134"},
"row303": {" TW": "6"," LW": "8"," Movie": "Alvin and the Chipmunks: The Squeakquel"," Studio": "n/a"," Weekend Gross": "$820"," Change": "+41.1%"," Screens / Avg.": "1"," Gross-to-Date": "-"," Week": "$820","": "$124,332"},
"row304": {" TW": "7"," LW": "7"," Movie": "Tooth Fairy"," Studio": "n/a"," Weekend Gross": "$668"," Change": "-20.9%"," Screens / Avg.": "1"," Gross-to-Date": "-"," Week": "$668","": "$27,263"},
"row305": {" TW": "8"," LW": "6"," Movie": "Percy Jackson & The Olympians: The Lightning Thief"," Studio": "n/a"," Weekend Gross": "$605"," Change": "-33.9%"," Screens / Avg.": "1"," Gross-to-Date": "-"," Week": "$605","": "$42,351"},
"row306": {" TW": "9"," LW": "11"," Movie": "Armored"," Studio": "Sony"," Weekend Gross": "$247"," Change": "+243.1%"," Screens / Avg.": "1"," Gross-to-Date": "-"," Week": "$247","": "$23,237"},
"row307": {" TW": "10"," LW": "9"," Movie": "A Prophet (Un prophte)"," Studio": "n/a"," Weekend Gross": "$207"," Change": "-50.0%"," Screens / Avg.": "1"," Gross-to-Date": "-"," Week": "$207","": "$2,809"},
"row308": {" TW": "11"," LW": "10"," Movie": "2012"," Studio": "Sony"," Weekend Gross": "$143"," Change": "+28.8%"," Screens / Avg.": "1"," Gross-to-Date": "-"," Week": "$143","": "$471,318"},
"row309": {" TW": "12"," LW": "-"," Movie": "Did You Hear About the Morgans?"," Studio": "Sony"," Weekend Gross": "$88"," Change": "-"," Screens / Avg.": "1"," Gross-to-Date": "-"," Week": "$88","": "$24,645"},
"row310": {" TW": " TW"," LW": " LW"," Movie": " Movie"," Studio": " Studio"," Weekend Gross": " Weekend Gross"," Change": " Change"," Screens / Avg.": " Screens"," Gross-to-Date": " Change / Avg."," Week": " Gross-to-Date","": " Week"},
"row311": {" TW": "1"," LW": "N"," Movie": "The Back-Up Plan"," Studio": "Sony"," Weekend Gross": "$8,162"," Change": "-"," Screens / Avg.": "1"," Gross-to-Date": "-"," Week": "$8,162","": "$8,162"},
"row312": {" TW": "2"," LW": "1"," Movie": "Date Night"," Studio": "n/a"," Weekend Gross": "$3,382"," Change": "-34.8%"," Screens / Avg.": "1"," Gross-to-Date": "-"," Week": "$3,382","": "$36,449"},
"row313": {" TW": "3"," LW": "2"," Movie": "Avatar"," Studio": "Fox"," Weekend Gross": "$2,722"," Change": "-41.0%"," Screens / Avg.": "1"," Gross-to-Date": "-1"," Week": "$2,722","": "$881,074"},
"row314": {" TW": "4"," LW": "3"," Movie": "The Bounty Hunter"," Studio": "Sony"," Weekend Gross": "$1,783"," Change": "-46.6%"," Screens / Avg.": "1"," Gross-to-Date": "-"," Week": "$1,783","": "$46,624"},
"row315": {" TW": "5"," LW": "5"," Movie": "My Name is Khan"," Studio": "n/a"," Weekend Gross": "$1,186"," Change": "-34.6%"," Screens / Avg.": "1"," Gross-to-Date": "-"," Week": "$1,186","": "$455,535"},
"row316": {" TW": "6"," LW": "7"," Movie": "Percy Jackson & The Olympians: The Lightning Thief"," Studio": "n/a"," Weekend Gross": "$915"," Change": "-38.8%"," Screens / Avg.": "1"," Gross-to-Date": "-"," Week": "$915","": "$41,548"},
"row317": {" TW": "7"," LW": "4"," Movie": "Tooth Fairy"," Studio": "n/a"," Weekend Gross": "$844"," Change": "-66.3%"," Screens / Avg.": "1"," Gross-to-Date": "-"," Week": "$844","": "$26,396"},
"row318": {" TW": "8"," LW": "6"," Movie": "Alvin and the Chipmunks: The Squeakquel"," Studio": "n/a"," Weekend Gross": "$581"," Change": "-63.1%"," Screens / Avg.": "1"," Gross-to-Date": "-"," Week": "$581","": "$123,361"},
"row319": {" TW": "9"," LW": "9"," Movie": "A Prophet (Un prophte)"," Studio": "n/a"," Weekend Gross": "$414"," Change": "-34.2%"," Screens / Avg.": "1"," Gross-to-Date": "-"," Week": "$414","": "$2,459"},
"row320": {" TW": "10"," LW": "8"," Movie": "2012"," Studio": "Sony"," Weekend Gross": "$111"," Change": "-86.9%"," Screens / Avg.": "1"," Gross-to-Date": "-"," Week": "$111","": "$471,095"},
"row321": {" TW": "11"," LW": "-"," Movie": "Armored"," Studio": "Sony"," Weekend Gross": "$72"," Change": "-"," Screens / Avg.": "1"," Gross-to-Date": "-"," Week": "$72","": "$22,910"},
"row322": {" TW": " TW"," LW": " LW"," Movie": " Movie"," Studio": " Studio"," Weekend Gross": " Weekend Gross"," Change": " Change"," Screens / Avg.": " Screens"," Gross-to-Date": " Change / Avg."," Week": " Gross-to-Date","": " Week"},
"row323": {" TW": "1"," LW": "1"," Movie": "Date Night"," Studio": "n/a"," Weekend Gross": "$5,183"," Change": "-7.7%"," Screens / Avg.": "1"," Gross-to-Date": "-"," Week": "$5,183","": "$32,184"},
"row324": {" TW": "2"," LW": "2"," Movie": "Avatar"," Studio": "Fox"," Weekend Gross": "$4,616"," Change": "+9.7%"," Screens / Avg.": "2"," Gross-to-Date": "-"," Week": "$2,308","": "$877,501"},
"row325": {" TW": "3"," LW": "4"," Movie": "The Bounty Hunter"," Studio": "Sony"," Weekend Gross": "$3,340"," Change": "+17.4%"," Screens / Avg.": "1"," Gross-to-Date": "-"," Week": "$3,340","": "$43,860"},
"row326": {" TW": "4"," LW": "5"," Movie": "Tooth Fairy"," Studio": "n/a"," Weekend Gross": "$2,507"," Change": "+9.0%"," Screens / Avg.": "1"," Gross-to-Date": "-"," Week": "$2,507","": "$25,433"},
"row327": {" TW": "5"," LW": "3"," Movie": "My Name is Khan"," Studio": "n/a"," Weekend Gross": "$1,814"," Change": "-45.5%"," Screens / Avg.": "1"," Gross-to-Date": "-1"," Week": "$1,814","": "$453,999"},
"row328": {" TW": "6"," LW": "7"," Movie": "Alvin and the Chipmunks: The Squeakquel"," Studio": "n/a"," Weekend Gross": "$1,573"," Change": "-0.7%"," Screens / Avg.": "1"," Gross-to-Date": "-"," Week": "$1,573","": "$122,701"},
"row329": {" TW": "7"," LW": "6"," Movie": "Percy Jackson & The Olympians: The Lightning Thief"," Studio": "n/a"," Weekend Gross": "$1,496"," Change": "-8.7%"," Screens / Avg.": "1"," Gross-to-Date": "-"," Week": "$1,496","": "$40,394"},
"row330": {" TW": "8"," LW": "9"," Movie": "2012"," Studio": "Sony"," Weekend Gross": "$844"," Change": "-"," Screens / Avg.": "1"," Gross-to-Date": "-"," Week": "$844","": "$470,721"},
"row331": {" TW": "9"," LW": "8"," Movie": "A Prophet (Un prophte)"," Studio": "n/a"," Weekend Gross": "$629"," Change": "-31.9%"," Screens / Avg.": "1"," Gross-to-Date": "-"," Week": "$629","": "$1,910"},
"row332": {" TW": " TW"," LW": " LW"," Movie": " Movie"," Studio": " Studio"," Weekend Gross": " Weekend Gross"," Change": " Change"," Screens / Avg.": " Screens / Avg."," Gross-to-Date": " Gross-to-Date"," Week": " Week","": ""},
"row333": {" TW": "1"," LW": "3"," Movie": "Date Night"," Studio": "n/a"," Weekend Gross": "$5,618"," Change": "-20.1%"," Screens / Avg.": "1"," Gross-to-Date": "$5,618"," Week": "$25,536","": "3"},
"row334": {" TW": "2"," LW": "1"," Movie": "Avatar"," Studio": "Fox"," Weekend Gross": "$4,207"," Change": "-51.9%"," Screens / Avg.": "2"," Gross-to-Date": "$2,104"," Week": "$871,984","": "19"},
"row335": {" TW": "3"," LW": "2"," Movie": "My Name is Khan"," Studio": "n/a"," Weekend Gross": "$3,329"," Change": "-55.1%"," Screens / Avg.": "2"," Gross-to-Date": "$1,665"," Week": "$451,621","": "10"},
"row336": {" TW": "4"," LW": "4"," Movie": "The Bounty Hunter"," Studio": "Sony"," Weekend Gross": "$2,846"," Change": "-37.4%"," Screens / Avg.": "1"," Gross-to-Date": "$2,846"," Week": "$39,714","": "5"},
"row337": {" TW": "5"," LW": "5"," Movie": "Tooth Fairy"," Studio": "n/a"," Weekend Gross": "$2,300"," Change": "-37.2%"," Screens / Avg.": "1"," Gross-to-Date": "$2,300"," Week": "$22,456","": "4"},
"row338": {" TW": "6"," LW": "7"," Movie": "Percy Jackson & The Olympians: The Lightning Thief"," Studio": "n/a"," Weekend Gross": "$1,639"," Change": "-42.2%"," Screens / Avg.": "1"," Gross-to-Date": "$1,639"," Week": "$38,626","": "9"},
"row339": {" TW": "7"," LW": "6"," Movie": "Alvin and the Chipmunks: The Squeakquel"," Studio": "n/a"," Weekend Gross": "$1,584"," Change": "-47.3%"," Screens / Avg.": "1"," Gross-to-Date": "$1,584"," Week": "$120,517","": "17"},
"row340": {" TW": "8"," LW": "N"," Movie": "A Prophet (Un prophte)"," Studio": "n/a"," Weekend Gross": "$923"," Change": "-"," Screens / Avg.": "1"," Gross-to-Date": "$923"," Week": "$1,218","": "1"},
"row341": {" TW": "9"," LW": "8"," Movie": "2012"," Studio": "Sony"," Weekend Gross": "$844"," Change": "-43.0%"," Screens / Avg.": "1"," Gross-to-Date": "$844"," Week": "$469,782","": "24"},
"row342": {" TW": "10"," LW": "9"," Movie": "Armored"," Studio": "Sony"," Weekend Gross": "$342"," Change": "-23.3%"," Screens / Avg.": "1"," Gross-to-Date": "$342"," Week": "$22,823","": "15"},
"row343": {" TW": "11"," LW": "10"," Movie": "Did You Hear About the Morgans?"," Studio": "Sony"," Weekend Gross": "$318"," Change": "+66.5%"," Screens / Avg.": "1"," Gross-to-Date": "$318"," Week": "$24,550","": "13"},
"row344": {" TW": " TW"," LW": " LW"," Movie": " Movie"," Studio": " Studio"," Weekend Gross": " Weekend Gross"," Change": " Change"," Screens / Avg.": " Screens / Avg."," Gross-to-Date": " Gross-to-Date"," Week": " Week","": ""},
"row345": {" TW": "1"," LW": "1"," Movie": "Avatar"," Studio": "Fox"," Weekend Gross": "$8,753"," Change": "+20.7%"," Screens / Avg.": "2"," Gross-to-Date": "$4,377"," Week": "$866,833","": "18"},
"row346": {" TW": "2"," LW": "-"," Movie": "My Name is Khan"," Studio": "n/a"," Weekend Gross": "$7,411"," Change": "-"," Screens / Avg.": "2"," Gross-to-Date": "$3,706"," Week": "$442,936","": "9"},
"row347": {" TW": "3"," LW": "4"," Movie": "Date Night"," Studio": "n/a"," Weekend Gross": "$7,029"," Change": "+42.6%"," Screens / Avg.": "1"," Gross-to-Date": "$7,029"," Week": "$18,040","": "2"},
"row348": {" TW": "4"," LW": "2"," Movie": "The Bounty Hunter"," Studio": "Sony"," Weekend Gross": "$4,546"," Change": "-16.5%"," Screens / Avg.": "1"," Gross-to-Date": "$4,546"," Week": "$34,472","": "4"},
"row349": {" TW": "5"," LW": "3"," Movie": "Tooth Fairy"," Studio": "n/a"," Weekend Gross": "$3,660"," Change": "-30.3%"," Screens / Avg.": "1"," Gross-to-Date": "$3,660"," Week": "$19,727","": "3"},
"row350": {" TW": "6"," LW": "6"," Movie": "Alvin and the Chipmunks: The Squeakquel"," Studio": "n/a"," Weekend Gross": "$3,008"," Change": "+87.2%"," Screens / Avg.": "1"," Gross-to-Date": "$3,008"," Week": "$118,767","": "16"},
"row351": {" TW": "7"," LW": "5"," Movie": "Percy Jackson & The Olympians: The Lightning Thief"," Studio": "n/a"," Weekend Gross": "$2,833"," Change": "+46.5%"," Screens / Avg.": "1"," Gross-to-Date": "$2,833"," Week": "$36,788","": "8"},
"row352": {" TW": "8"," LW": "7"," Movie": "2012"," Studio": "Sony"," Weekend Gross": "$1,480"," Change": "+31.0%"," Screens / Avg.": "1"," Gross-to-Date": "$1,480"," Week": "$467,546","": "23"},
"row353": {" TW": "9"," LW": "9"," Movie": "Armored"," Studio": "Sony"," Weekend Gross": "$446"," Change": "+36.8%"," Screens / Avg.": "1"," Gross-to-Date": "$446"," Week": "$22,194","": "14"},
"row354": {" TW": "10"," LW": "8"," Movie": "Did You Hear About the Morgans?"," Studio": "Sony"," Weekend Gross": "$191"," Change": "-59.3%"," Screens / Avg.": "1"," Gross-to-Date": "$191"," Week": "$23,985","": "12"},
"row355": {" TW": " TW"," LW": " LW"," Movie": " Movie"," Studio": " Studio"," Weekend Gross": " Weekend Gross"," Change": " Change"," Screens / Avg.": " Screens / Avg."," Gross-to-Date": " Gross-to-Date"," Week": " Week","": ""},
"row356": {" TW": "1"," LW": "2"," Movie": "Avatar"," Studio": "Fox"," Weekend Gross": "$7,255"," Change": "-19.4%"," Screens / Avg.": "2"," Gross-to-Date": "$3,628"," Week": "$852,997","": "17"},
"row357": {" TW": "2"," LW": "3"," Movie": "The Bounty Hunter"," Studio": "Sony"," Weekend Gross": "$5,443"," Change": "-37.8%"," Screens / Avg.": "1"," Gross-to-Date": "$5,443"," Week": "$28,406","": "3"},
"row358": {" TW": "3"," LW": "4"," Movie": "Tooth Fairy"," Studio": "n/a"," Weekend Gross": "$5,252"," Change": "+3.1%"," Screens / Avg.": "1"," Gross-to-Date": "$5,252"," Week": "$13,822","": "2"},
"row359": {" TW": "4"," LW": "N"," Movie": "Date Night"," Studio": "n/a"," Weekend Gross": "$4,928"," Change": "-"," Screens / Avg.": "1"," Gross-to-Date": "$4,928"," Week": "$7,676","": "1"},
"row360": {" TW": "5"," LW": "5"," Movie": "Percy Jackson & The Olympians: The Lightning Thief"," Studio": "n/a"," Weekend Gross": "$1,934"," Change": "-20.1%"," Screens / Avg.": "1"," Gross-to-Date": "$1,934"," Week": "$33,239","": "7"},
"row361": {" TW": "6"," LW": "6"," Movie": "Alvin and the Chipmunks: The Squeakquel"," Studio": "n/a"," Weekend Gross": "$1,607"," Change": "-17.3%"," Screens / Avg.": "1"," Gross-to-Date": "$1,607"," Week": "$113,451","": "15"},
"row362": {" TW": "7"," LW": "7"," Movie": "2012"," Studio": "Sony"," Weekend Gross": "$1,130"," Change": "-11.8%"," Screens / Avg.": "1"," Gross-to-Date": "$1,130"," Week": "$465,787","": "22"},
"row363": {" TW": "8"," LW": "9"," Movie": "Did You Hear About the Morgans?"," Studio": "Sony"," Weekend Gross": "$469"," Change": "+126.6%"," Screens / Avg.": "1"," Gross-to-Date": "$469"," Week": "$23,658","": "11"},
"row364": {" TW": "9"," LW": "8"," Movie": "Armored"," Studio": "Sony"," Weekend Gross": "$326"," Change": "-4.7%"," Screens / Avg.": "1"," Gross-to-Date": "$326"," Week": "$21,669","": "13"},
"row365": {" TW": " TW"," LW": " LW"," Movie": " Movie"," Studio": " Studio"," Weekend Gross": " Weekend Gross"," Change": " Change"," Screens / Avg.": " Screens / Avg."," Gross-to-Date": " Gross-to-Date"," Week": " Week","": ""},
"row366": {" TW": "1"," LW": "1"," Movie": "My Name is Khan"," Studio": "n/a"," Weekend Gross": "$11,069"," Change": "-17.2%"," Screens / Avg.": "3"," Gross-to-Date": "$3,690"," Week": "$425,825","": "7"},
"row367": {" TW": "2"," LW": "2"," Movie": "Avatar"," Studio": "Fox"," Weekend Gross": "$9,005"," Change": "-17.7%"," Screens / Avg.": "2"," Gross-to-Date": "$4,503"," Week": "$842,798","": "16"},
"row368": {" TW": "3"," LW": "3"," Movie": "The Bounty Hunter"," Studio": "Sony"," Weekend Gross": "$8,745"," Change": "+13.2%"," Screens / Avg.": "1"," Gross-to-Date": "$8,745"," Week": "$20,181","": "2"},
"row369": {" TW": "4"," LW": "N"," Movie": "Tooth Fairy"," Studio": "n/a"," Weekend Gross": "$5,093"," Change": "-"," Screens / Avg.": "1"," Gross-to-Date": "$5,093"," Week": "$7,440","": "1"},
"row370": {" TW": "5"," LW": "4"," Movie": "Percy Jackson & The Olympians: The Lightning Thief"," Studio": "n/a"," Weekend Gross": "$2,419"," Change": "+19.7%"," Screens / Avg.": "1"," Gross-to-Date": "$2,419"," Week": "$30,660","": "6"},
"row371": {" TW": "6"," LW": "5"," Movie": "Alvin and the Chipmunks: The Squeakquel"," Studio": "n/a"," Weekend Gross": "$1,942"," Change": "+2.1%"," Screens / Avg.": "1"," Gross-to-Date": "$1,942"," Week": "$111,135","": "14"},
"row372": {" TW": "7"," LW": "6"," Movie": "2012"," Studio": "Sony"," Weekend Gross": "$1,281"," Change": "+0.6%"," Screens / Avg.": "1"," Gross-to-Date": "$1,281"," Week": "$464,196","": "21"},
"row373": {" TW": "8"," LW": "7"," Movie": "Armored"," Studio": "Sony"," Weekend Gross": "$342"," Change": "-65.4%"," Screens / Avg.": "1"," Gross-to-Date": "$342"," Week": "$21,208","": "12"},
"row374": {" TW": "9"," LW": "8"," Movie": "Did You Hear About the Morgans?"," Studio": "Sony"," Weekend Gross": "$207"," Change": "-68.3%"," Screens / Avg.": "1"," Gross-to-Date": "$207"," Week": "$23,078","": "10"},
"row375": {" TW": " TW"," LW": " LW"," Movie": " Movie"," Studio": " Studio"," Weekend Gross": " Weekend Gross"," Change": " Change"," Screens / Avg.": " Screens / Avg."," Gross-to-Date": " Gross-to-Date"," Week": " Week","": ""},
"row376": {" TW": "1"," LW": "1"," Movie": "My Name is Khan"," Studio": "n/a"," Weekend Gross": "$13,364"," Change": "-20.0%"," Screens / Avg.": "3"," Gross-to-Date": "$4,455"," Week": "$412,327","": "6"},
"row377": {" TW": "2"," LW": "2"," Movie": "Avatar"," Studio": "Fox"," Weekend Gross": "$10,947"," Change": "-17.4%"," Screens / Avg.": "2"," Gross-to-Date": "$5,474"," Week": "$830,807","": "15"},
"row378": {" TW": "3"," LW": "N"," Movie": "The Bounty Hunter"," Studio": "Sony"," Weekend Gross": "$7,724"," Change": "-"," Screens / Avg.": "1"," Gross-to-Date": "$7,724"," Week": "$7,724","": "1"},
"row379": {" TW": "4"," LW": "3"," Movie": "Percy Jackson & The Olympians: The Lightning Thief"," Studio": "n/a"," Weekend Gross": "$2,021"," Change": "-43.3%"," Screens / Avg.": "1"," Gross-to-Date": "$2,021"," Week": "$27,526","": "5"},
"row380": {" TW": "5"," LW": "4"," Movie": "Alvin and the Chipmunks: The Squeakquel"," Studio": "n/a"," Weekend Gross": "$1,902"," Change": "+1.3%"," Screens / Avg.": "1"," Gross-to-Date": "$1,902"," Week": "$108,425","": "13"},
"row381": {" TW": "6"," LW": "5"," Movie": "2012"," Studio": "Sony"," Weekend Gross": "$1,273"," Change": "+3.2%"," Screens / Avg.": "1"," Gross-to-Date": "$1,273"," Week": "$462,413","": "20"},
"row382": {" TW": "7"," LW": "7"," Movie": "Armored"," Studio": "Sony"," Weekend Gross": "$987"," Change": "+226.8%"," Screens / Avg.": "1"," Gross-to-Date": "$987"," Week": "$20,547","": "11"},
"row383": {" TW": "8"," LW": "6"," Movie": "Did You Hear About the Morgans?"," Studio": "Sony"," Weekend Gross": "$653"," Change": "-"," Screens / Avg.": "1"," Gross-to-Date": "$653"," Week": "$22,632","": "9"},
"row384": {" TW": " TW"," LW": " LW"," Movie": " Movie"," Studio": " Studio"," Weekend Gross": " Weekend Gross"," Change": " Change"," Screens / Avg.": " Screens / Avg."," Gross-to-Date": " Gross-to-Date"," Week": " Week","": ""},
"row385": {" TW": "1"," LW": "1"," Movie": "My Name is Khan"," Studio": "n/a"," Weekend Gross": "$16,701"," Change": "-35.0%"," Screens / Avg.": "3"," Gross-to-Date": "$5,567"," Week": "$390,750","": "5"},
"row386": {" TW": "2"," LW": "2"," Movie": "Avatar"," Studio": "Fox"," Weekend Gross": "$13,255"," Change": "-10.6%"," Screens / Avg.": "2"," Gross-to-Date": "$6,628"," Week": "$815,865","": "14"},
"row387": {" TW": "3"," LW": "3"," Movie": "Percy Jackson & The Olympians: The Lightning Thief"," Studio": "n/a"," Weekend Gross": "$3,565"," Change": "+5.4%"," Screens / Avg.": "1"," Gross-to-Date": "$3,565"," Week": "$24,677","": "4"},
"row388": {" TW": "4"," LW": "4"," Movie": "Alvin and the Chipmunks: The Squeakquel"," Studio": "n/a"," Weekend Gross": "$1,878"," Change": "-21.9%"," Screens / Avg.": "1"," Gross-to-Date": "$1,878"," Week": "$106,037","": "12"},
"row389": {" TW": "5"," LW": "5"," Movie": "2012"," Studio": "Sony"," Weekend Gross": "$1,233"," Change": "-11.5%"," Screens / Avg.": "1"," Gross-to-Date": "$1,233"," Week": "$460,846","": "19"},
"row390": {" TW": "6"," LW": "6"," Movie": "Did You Hear About the Morgans?"," Studio": "Sony"," Weekend Gross": "$653"," Change": "+6.5%"," Screens / Avg.": "1"," Gross-to-Date": "$653"," Week": "$21,749","": "8"},
"row391": {" TW": "7"," LW": "7"," Movie": "Armored"," Studio": "Sony"," Weekend Gross": "$302"," Change": "-31.1%"," Screens / Avg.": "1"," Gross-to-Date": "$302"," Week": "$19,337","": "10"},
"row392": {" TW": " TW"," LW": " LW"," Movie": " Movie"," Studio": " Studio"," Weekend Gross": " Weekend Gross"," Change": " Change"," Screens / Avg.": " Screens / Avg."," Gross-to-Date": " Gross-to-Date"," Week": " Week","": ""},
"row393": {" TW": "1"," LW": "1"," Movie": "My Name is Khan"," Studio": "n/a"," Weekend Gross": "$25,696"," Change": "-30.4%"," Screens / Avg.": "3"," Gross-to-Date": "$8,565"," Week": "$374,047","": "4"},
"row394": {" TW": "2"," LW": "2"," Movie": "Avatar"," Studio": "Fox"," Weekend Gross": "$14,823"," Change": "-26.6%"," Screens / Avg.": "2"," Gross-to-Date": "$7,412"," Week": "$798,740","": "13"},
"row395": {" TW": "3"," LW": "3"," Movie": "Percy Jackson & The Olympians: The Lightning Thief"," Studio": "n/a"," Weekend Gross": "$3,382"," Change": "-22.2%"," Screens / Avg.": "1"," Gross-to-Date": "$3,382"," Week": "$20,404","": "3"},
"row396": {" TW": "4"," LW": "4"," Movie": "Alvin and the Chipmunks: The Squeakquel"," Studio": "n/a"," Weekend Gross": "$2,403"," Change": "-21.4%"," Screens / Avg.": "1"," Gross-to-Date": "$2,403"," Week": "$103,777","": "11"},
"row397": {" TW": "5"," LW": "5"," Movie": "2012"," Studio": "Sony"," Weekend Gross": "$1,393"," Change": "-14.2%"," Screens / Avg.": "1"," Gross-to-Date": "$1,393"," Week": "$459,119","": "18"},
"row398": {" TW": "6"," LW": "6"," Movie": "Did You Hear About the Morgans?"," Studio": "Sony"," Weekend Gross": "$613"," Change": "-8.2%"," Screens / Avg.": "1"," Gross-to-Date": "$613"," Week": "$20,857","": "7"},
"row399": {" TW": "7"," LW": "7"," Movie": "Armored"," Studio": "Sony"," Weekend Gross": "$438"," Change": "-28.6%"," Screens / Avg.": "1"," Gross-to-Date": "$438"," Week": "$18,884","": "9"},
"row400": {" TW": " TW"," LW": " LW"," Movie": " Movie"," Studio": " Studio"," Weekend Gross": " Weekend Gross"," Change": " Change"," Screens / Avg.": " Screens"," Gross-to-Date": " Change / Avg."," Week": " Gross-to-Date","": " Week"},
"row401": {" TW": "1"," LW": "1"," Movie": "My Name is Khan"," Studio": "n/a"," Weekend Gross": "$36,943"," Change": "-61.3%"," Screens / Avg.": "3"," Gross-to-Date": "-3"," Week": "$12,314","": "$341,213"},
"row402": {" TW": "2"," LW": "2"," Movie": "Avatar"," Studio": "Fox"," Weekend Gross": "$20,194"," Change": "-35.7%"," Screens / Avg.": "2"," Gross-to-Date": "-"," Week": "$10,097","": "$779,013"},
"row403": {" TW": "3"," LW": "3"," Movie": "Percy Jackson & The Olympians: The Lightning Thief"," Studio": "n/a"," Weekend Gross": "$4,345"," Change": "-49.2%"," Screens / Avg.": "1"," Gross-to-Date": "-"," Week": "$4,345","": "$16,178"},
"row404": {" TW": "4"," LW": "4"," Movie": "Alvin and the Chipmunks: The Squeakquel"," Studio": "n/a"," Weekend Gross": "$3,056"," Change": "-22.4%"," Screens / Avg.": "1"," Gross-to-Date": "-"," Week": "$3,056","": "$100,857"},
"row405": {" TW": "5"," LW": "5"," Movie": "2012"," Studio": "Sony"," Weekend Gross": "$1,623"," Change": "-14.3%"," Screens / Avg.": "1"," Gross-to-Date": "-"," Week": "$1,623","": "$457,169"},
"row406": {" TW": "6"," LW": "6"," Movie": "Did You Hear About the Morgans?"," Studio": "Sony"," Weekend Gross": "$668"," Change": "-44.4%"," Screens / Avg.": "1"," Gross-to-Date": "-"," Week": "$668","": "$20,077"},
"row407": {" TW": "7"," LW": "7"," Movie": "Armored"," Studio": "Sony"," Weekend Gross": "$613"," Change": "-37.4%"," Screens / Avg.": "1"," Gross-to-Date": "-"," Week": "$613","": "$18,383"},
"row408": {" TW": " TW"," LW": " LW"," Movie": " Movie"," Studio": " Studio"," Weekend Gross": " Weekend Gross"," Change": " Change"," Screens / Avg.": " Screens"," Gross-to-Date": " Change / Avg."," Week": " Gross-to-Date","": " Week"},
"row409": {" TW": "1"," LW": "1"," Movie": "My Name is Khan"," Studio": "n/a"," Weekend Gross": "$95,520"," Change": "-35.8%"," Screens / Avg.": "6"," Gross-to-Date": "-"," Week": "$15,920","": "$292,368"},
"row410": {" TW": "2"," LW": "2"," Movie": "Avatar"," Studio": "Fox"," Weekend Gross": "$31,399"," Change": "-10.2%"," Screens / Avg.": "2"," Gross-to-Date": "-"," Week": "$15,700","": "$752,718"},
"row411": {" TW": "3"," LW": "N"," Movie": "Percy Jackson & The Olympians: The Lightning Thief"," Studio": "n/a"," Weekend Gross": "$8,555"," Change": "-"," Screens / Avg.": "1"," Gross-to-Date": "-"," Week": "$8,555","": "$10,783"},
"row412": {" TW": "4"," LW": "3"," Movie": "Alvin and the Chipmunks: The Squeakquel"," Studio": "n/a"," Weekend Gross": "$3,939"," Change": "-27.1%"," Screens / Avg.": "1"," Gross-to-Date": "-"," Week": "$3,939","": "$97,331"},
"row413": {" TW": "5"," LW": "4"," Movie": "2012"," Studio": "Sony"," Weekend Gross": "$1,894"," Change": "-51.1%"," Screens / Avg.": "1"," Gross-to-Date": "-1"," Week": "$1,894","": "$455,092"},
"row414": {" TW": "6"," LW": "5"," Movie": "Did You Hear About the Morgans?"," Studio": "Sony"," Weekend Gross": "$1,202"," Change": "+10.3%"," Screens / Avg.": "1"," Gross-to-Date": "-"," Week": "$1,202","": "$19,154"},
"row415": {" TW": "7"," LW": "6"," Movie": "Armored"," Studio": "Sony"," Weekend Gross": "$979"," Change": "+7.9%"," Screens / Avg.": "1"," Gross-to-Date": "-"," Week": "$979","": "$17,276"},
"row416": {" TW": " TW"," LW": " LW"," Movie": " Movie"," Studio": " Studio"," Weekend Gross": " Weekend Gross"," Change": " Change"," Screens / Avg.": " Screens / Avg."," Gross-to-Date": " Gross-to-Date"," Week": " Week","": ""},
"row417": {" TW": "1"," LW": "N"," Movie": "My Name is Khan"," Studio": "n/a"," Weekend Gross": "$148,800"," Change": "-"," Screens / Avg.": "6"," Gross-to-Date": "$24,800"," Week": "$148,800","": "1"},
"row418": {" TW": "2"," LW": "1"," Movie": "Avatar"," Studio": "Fox"," Weekend Gross": "$34,974"," Change": "-38.4%"," Screens / Avg.": "2"," Gross-to-Date": "$17,487"," Week": "$712,918","": "10"},
"row419": {" TW": "3"," LW": "2"," Movie": "Alvin and the Chipmunks: The Squeakquel"," Studio": "n/a"," Weekend Gross": "$5,403"," Change": "-40.9%"," Screens / Avg.": "1"," Gross-to-Date": "$5,403"," Week": "$92,899","": "8"},
"row420": {" TW": "4"," LW": "3"," Movie": "2012"," Studio": "Sony"," Weekend Gross": "$3,873"," Change": "-33.5%"," Screens / Avg.": "2"," Gross-to-Date": "$1,937"," Week": "$452,206","": "15"},
"row421": {" TW": "5"," LW": "4"," Movie": "Did You Hear About the Morgans?"," Studio": "Sony"," Weekend Gross": "$1,090"," Change": "-60.3%"," Screens / Avg.": "1"," Gross-to-Date": "$1,090"," Week": "$17,555","": "4"},
"row422": {" TW": "6"," LW": "5"," Movie": "Armored"," Studio": "Sony"," Weekend Gross": "$907"," Change": "-53.1%"," Screens / Avg.": "1"," Gross-to-Date": "$907"," Week": "$15,892","": "6"},
"row423": {" TW": " TW"," LW": " LW"," Movie": " Movie"," Studio": " Studio"," Weekend Gross": " Weekend Gross"," Change": " Change"," Screens / Avg.": " Screens"," Gross-to-Date": " Change / Avg."," Week": " Gross-to-Date","": " Week"},
"row424": {" TW": "1"," LW": "1"," Movie": "Avatar"," Studio": "Fox"," Weekend Gross": "$56,813"," Change": "+12.7%"," Screens / Avg.": "2"," Gross-to-Date": "-"," Week": "$28,407","": "$665,922"},
"row425": {" TW": "2"," LW": "2"," Movie": "Alvin and the Chipmunks: The Squeakquel"," Studio": "n/a"," Weekend Gross": "$9,136"," Change": "+33.5%"," Screens / Avg.": "1"," Gross-to-Date": "-"," Week": "$9,136","": "$86,405"},
"row426": {" TW": "3"," LW": "4"," Movie": "2012"," Studio": "Sony"," Weekend Gross": "$5,825"," Change": "+71.0%"," Screens / Avg.": "2"," Gross-to-Date": "+1"," Week": "$2,913","": "$443,758"},
"row427": {" TW": "4"," LW": "3"," Movie": "Did You Hear About the Morgans?"," Studio": "Sony"," Weekend Gross": "$2,745"," Change": "-31.0%"," Screens / Avg.": "1"," Gross-to-Date": "-"," Week": "$2,745","": "$14,515"},
"row428": {" TW": "5"," LW": "5"," Movie": "Armored"," Studio": "Sony"," Weekend Gross": "$1,934"," Change": "+10.0%"," Screens / Avg.": "1"," Gross-to-Date": "-"," Week": "$1,934","": "$13,751"},
"row429": {" TW": "6"," LW": "7"," Movie": " Cloudy with a Chance of Meatballs"," Studio": "Sony"," Weekend Gross": "$1,401"," Change": "+144.5%"," Screens / Avg.": "1"," Gross-to-Date": "-"," Week": "$1,401","": "$103,527"},
"row430": {" TW": "7"," LW": "6"," Movie": "Step Father (2009)"," Studio": "Sony"," Weekend Gross": "$1,353"," Change": "+80.9%"," Screens / Avg.": "1"," Gross-to-Date": "-"," Week": "$1,353","": "$15,860"},
"row431": {" TW": " TW"," LW": " LW"," Movie": " Movie"," Studio": " Studio"," Weekend Gross": " Weekend Gross"," Change": " Change"," Screens / Avg.": " Screens"," Gross-to-Date": " Change / Avg."," Week": " Gross-to-Date","": " Week"},
"row432": {" TW": "1"," LW": "1"," Movie": "Avatar"," Studio": "Fox"," Weekend Gross": "$50,394"," Change": "-0.1%"," Screens / Avg.": "2"," Gross-to-Date": "-"," Week": "$25,197","": "$573,623"},
"row433": {" TW": "2"," LW": "2"," Movie": "Alvin and the Chipmunks: The Squeakquel"," Studio": "n/a"," Weekend Gross": "$6,844"," Change": "-16.3%"," Screens / Avg.": "1"," Gross-to-Date": "-"," Week": "$6,844","": "$72,074"},
"row434": {" TW": "3"," LW": "4"," Movie": "Did You Hear About the Morgans?"," Studio": "Sony"," Weekend Gross": "$3,979"," Change": "-2.3%"," Screens / Avg.": "1"," Gross-to-Date": "-"," Week": "$3,979","": "$9,772"},
"row435": {" TW": "4"," LW": "3"," Movie": "2012"," Studio": "Sony"," Weekend Gross": "$3,406"," Change": "-18.2%"," Screens / Avg.": "1"," Gross-to-Date": "-1"," Week": "$3,406","": "$435,688"},
"row436": {" TW": "5"," LW": "5"," Movie": "Armored"," Studio": "Sony"," Weekend Gross": "$1,759"," Change": "+97.4%"," Screens / Avg.": "1"," Gross-to-Date": "-"," Week": "$1,759","": "$10,950"},
"row437": {" TW": "6"," LW": "-"," Movie": "Step Father (2009)"," Studio": "Sony"," Weekend Gross": "$748"," Change": "-"," Screens / Avg.": "1"," Gross-to-Date": "-"," Week": "$748","": "$13,934"},
"row438": {" TW": "7"," LW": "6"," Movie": " Cloudy with a Chance of Meatballs"," Studio": "Sony"," Weekend Gross": "$573"," Change": "+38.4%"," Screens / Avg.": "1"," Gross-to-Date": "-"," Week": "$573","": "$101,848"},
"row439": {" TW": " TW"," LW": " LW"," Movie": " Movie"," Studio": " Studio"," Weekend Gross": " Weekend Gross"," Change": " Change"," Screens / Avg.": " Screens"," Gross-to-Date": " Change / Avg."," Week": " Gross-to-Date","": " Week"},
"row440": {" TW": "1"," LW": "1"," Movie": "Avatar"," Studio": "Fox"," Weekend Gross": "$50,434"," Change": "-1.1%"," Screens / Avg.": "2"," Gross-to-Date": "-"," Week": "$25,217","": "$501,704"},
"row441": {" TW": "2"," LW": "2"," Movie": "Alvin and the Chipmunks: The Squeakquel"," Studio": "n/a"," Weekend Gross": "$8,181"," Change": "-29.6%"," Screens / Avg.": "1"," Gross-to-Date": "-"," Week": "$8,181","": "$62,851"},
"row442": {" TW": "3"," LW": "3"," Movie": "2012"," Studio": "Sony"," Weekend Gross": "$4,162"," Change": "-48.0%"," Screens / Avg.": "2"," Gross-to-Date": "+1"," Week": "$2,081","": "$430,588"},
"row443": {" TW": "4"," LW": "-"," Movie": "Did You Hear About the Morgans?"," Studio": "Sony"," Weekend Gross": "$4,074"," Change": "-"," Screens / Avg.": "1"," Gross-to-Date": "-"," Week": "$4,074","": "$4,074"},
"row444": {" TW": "5"," LW": "4"," Movie": "Armored"," Studio": "Sony"," Weekend Gross": "$891"," Change": "-69.2%"," Screens / Avg.": "1"," Gross-to-Date": "-"," Week": "$891","": "$8,507"},
"row445": {" TW": "6"," LW": "7"," Movie": " Cloudy with a Chance of Meatballs"," Studio": "Sony"," Weekend Gross": "$414"," Change": "-46.9%"," Screens / Avg.": "1"," Gross-to-Date": "-"," Week": "$414","": "$101,116"},
"row446": {" TW": " TW"," LW": " LW"," Movie": " Movie"," Studio": " Studio"," Weekend Gross": " Weekend Gross"," Change": " Change"," Screens / Avg.": " Screens"," Gross-to-Date": " Change / Avg."," Week": " Gross-to-Date","": " Week"},
"row447": {" TW": "1"," LW": "1"," Movie": "Avatar"," Studio": "Fox"," Weekend Gross": "$50,989"," Change": "+8.5%"," Screens / Avg.": "2"," Gross-to-Date": "-1"," Week": "$25,495","": "$349,982"},
"row448": {" TW": "2"," LW": "2"," Movie": "Alvin and the Chipmunks: The Squeakquel"," Studio": "n/a"," Weekend Gross": "$11,618"," Change": "-4.0%"," Screens / Avg.": "1"," Gross-to-Date": "-"," Week": "$11,618","": "$40,012"},
"row449": {" TW": "3"," LW": "3"," Movie": "2012"," Studio": "Sony"," Weekend Gross": "$7,998"," Change": "+1.5%"," Screens / Avg.": "1"," Gross-to-Date": "-1"," Week": "$7,998","": "$417,409"},
"row450": {" TW": "4"," LW": "N"," Movie": "Armored"," Studio": "Sony"," Weekend Gross": "$2,897"," Change": "-"," Screens / Avg.": "1"," Gross-to-Date": "-"," Week": "$2,897","": "$2,897"},
"row451": {" TW": "5"," LW": "4"," Movie": "Zombieland"," Studio": "Sony"," Weekend Gross": "$1,027"," Change": "+7.5%"," Screens / Avg.": "1"," Gross-to-Date": "-"," Week": "$1,027","": "$24,354"},
"row452": {" TW": "6"," LW": "6"," Movie": "Step Father (2009)"," Studio": "Sony"," Weekend Gross": "$963"," Change": "+39.2%"," Screens / Avg.": "1"," Gross-to-Date": "-"," Week": "$963","": "$10,974"},
"row453": {" TW": "7"," LW": "5"," Movie": " Cloudy with a Chance of Meatballs"," Studio": "Sony"," Weekend Gross": "$780"," Change": "-17.9%"," Screens / Avg.": "1"," Gross-to-Date": "-"," Week": "$780","": "$100,017"},
"row454": {" TW": " TW"," LW": " LW"," Movie": " Movie"," Studio": " Studio"," Weekend Gross": " Weekend Gross"," Change": " Change"," Screens / Avg.": " Screens"," Gross-to-Date": " Change / Avg."," Week": " Gross-to-Date","": " Week"},
"row455": {" TW": "1"," LW": "1"," Movie": "Avatar"," Studio": "Fox"," Weekend Gross": "$47,018"," Change": "-28.0%"," Screens / Avg.": "3"," Gross-to-Date": "+1"," Week": "$15,673","": "$298,993"},
"row456": {" TW": "2"," LW": "2"," Movie": "Alvin and the Chipmunks: The Squeakquel"," Studio": "n/a"," Weekend Gross": "$12,104"," Change": "-6.9%"," Screens / Avg.": "1"," Gross-to-Date": "-"," Week": "$12,104","": "$28,394"},
"row457": {" TW": "3"," LW": "3"," Movie": "2012"," Studio": "Sony"," Weekend Gross": "$7,878"," Change": "-31.9%"," Screens / Avg.": "2"," Gross-to-Date": "-"," Week": "$3,939","": "$406,626"},
"row458": {" TW": "4"," LW": "5"," Movie": "Zombieland"," Studio": "Sony"," Weekend Gross": "$955"," Change": "-27.3%"," Screens / Avg.": "1"," Gross-to-Date": "-"," Week": "$955","": "$22,921"},
"row459": {" TW": "5"," LW": "6"," Movie": " Cloudy with a Chance of Meatballs"," Studio": "Sony"," Weekend Gross": "$950"," Change": "+38.9%"," Screens / Avg.": "1"," Gross-to-Date": "-"," Week": "$950","": "$99,179"},
"row460": {" TW": "6"," LW": "4"," Movie": "Step Father (2009)"," Studio": "Sony"," Weekend Gross": "$692"," Change": "-59.5%"," Screens / Avg.": "1"," Gross-to-Date": "-"," Week": "$692","": "$9,610"},
"row461": {" TW": " TW"," LW": " LW"," Movie": " Movie"," Studio": " Studio"," Weekend Gross": " Weekend Gross"," Change": " Change"," Screens / Avg.": " Screens"," Gross-to-Date": " Change / Avg."," Week": " Gross-to-Date","": " Week"},
"row462": {" TW": "1"," LW": "1"," Movie": "Avatar"," Studio": "Fox"," Weekend Gross": "$65,300"," Change": "+46.0%"," Screens / Avg.": "2"," Gross-to-Date": "-"," Week": "$32,650","": "$223,855"},
"row463": {" TW": "2"," LW": "N"," Movie": "Alvin and the Chipmunks: The Squeakquel"," Studio": "n/a"," Weekend Gross": "$13,003"," Change": "-"," Screens / Avg.": "1"," Gross-to-Date": "-"," Week": "$13,003","": "$14,603"},
"row464": {" TW": "3"," LW": "2"," Movie": "2012"," Studio": "Sony"," Weekend Gross": "$11,571"," Change": "+16.3%"," Screens / Avg.": "2"," Gross-to-Date": "+1"," Week": "$5,786","": "$395,430"},
"row465": {" TW": "4"," LW": "3"," Movie": "Step Father (2009)"," Studio": "Sony"," Weekend Gross": "$1,708"," Change": "+36.4%"," Screens / Avg.": "1"," Gross-to-Date": "-"," Week": "$1,708","": "$8,576"},
"row466": {" TW": "5"," LW": "4"," Movie": "Zombieland"," Studio": "Sony"," Weekend Gross": "$1,313"," Change": "+50.1%"," Screens / Avg.": "1"," Gross-to-Date": "-"," Week": "$1,313","": "$21,696"},
"row467": {" TW": "6"," LW": "5"," Movie": " Cloudy with a Chance of Meatballs"," Studio": "Sony"," Weekend Gross": "$684"," Change": "-13.2%"," Screens / Avg.": "1"," Gross-to-Date": "-"," Week": "$684","": "$98,094"}}
